Workbook
Name ExpenseCats: Settings!$B$8:$B$37
Name IncomeCats: Settings!$D$8:$D$37
Name Accounts: Settings!$F$8:$F$37
Name Months: Settings!$H$8:$H$19

Sheet Start Here
B2: Tidy Money — Budget Dashboard
B3: Thank you for your purchase. This page gets you set up in about 10 minutes.
B5: USING GOOGLE SHEETS?
B6: 1 | C6: Upload this file to Google Drive, open it, then choose File → Save as Google Sheets. (Or in Sheets: File → Import → Upload → 'Replace spreadsheet'.) Every formula, dropdown and chart is compatible.
B7: USING EXCEL?
B8: 1 | C8: Just open the file. If Excel shows 'Protected View', click Enable Editing. Works on Mac & Windows, Excel 2016 or newer and Microsoft 365. Apple Numbers opens it too (charts may look slightly different).
B9: SET-UP (ONCE)
B10: 2 | C10: Settings tab → set your budget year and edit the category and account lists to match your life. Keep names short.
B11: 3 | C11: Budget Plan tab → type a default monthly amount for each income and expense category. Any single month can be overwritten later.
B12: 4 | C12: Transactions tab → delete the example rows (they say 'example' in Notes) and start logging. Date, description, Income/Expense, category, amount. That's it.
B13: EVERY WEEK (5 MINUTES)
B14: 5 | C14: Add your transactions. Open the Dashboard, pick the month in the yellow dropdown, and see what's left in each category.
B15: 6 | C15: Savings Goals → update 'Saved so far'. Debt Payoff → update balances. Net Worth → once a month, type your balances.
B16: GOOD TO KNOW
B17: • | C17: Yellow cells are for you to type in. White and green cells are formulas — leave them alone (if you break one, just undo).
B18: • | C18: Savings rate = (income − expenses) ÷ income for the selected month. 'Savings transfers' counts as an expense so money you move to savings isn't double-counted.
B19: • | C19: Couples: share the Google Sheet with your partner; you can both log from your phones with the Google Sheets app.
B20: • | C20: New year? Save a copy, change the year in Settings, clear the Transactions rows, and keep your plan.
B21: • | C21: Need help or a refund within 7 days? Reply to your Whop receipt email.
C23: © Tidy Money. For personal use. Please don't resell or redistribute this file.

Sheet Dashboard
B2: Tidy Money — Budget Dashboard
B3: Pick a month → | C3: =DATE(Settings!$C$5,9,1) | E3: (dropdown – all tabs marked 'selected month' follow this cell)
C5: Income this month | F5: Spent this month | I5: Left over | L5: Savings rate
C6: =SUMIFS(Transactions!$F$7:$F$1006,Transactions!$D$7:$D$1006,"Income",Transactions!$I$7:$I$1006,Dashboard!$C$3) | F6: =SUMIFS(Transactions!$F$7:$F$1006,Transactions!$D$7:$D$1006,"Expense",Transactions!$I$7:$I$1006,Dashboard!$C$3) | I6: =C6-F6 | L6: =IF(C6=0,0,I6/C6)
C8: Planned expenses | F8: Actual vs plan | I8: Planned income | L8: Transactions logged
C9: =IFERROR(INDEX('Budget Plan'!$D$51:$O$51,MATCH(Dashboard!$C$3,'Budget Plan'!$D$6:$O$6,0)),0) | F9: =F6-C9 | I9: =IFERROR(INDEX('Budget Plan'!$D$18:$O$18,MATCH(Dashboard!$C$3,'Budget Plan'!$D$6:$O$6,0)),0) | L9: =COUNTIFS(Transactions!$I$7:$I$1006,Dashboard!$C$3)
C11: Category | D11: Planned | E11: Actual | F11: Left | G11: % used | I11: Top spending | J11: Amount
C12: =IF(Settings!B8="","",Settings!B8) | D12: =IF($C12="","",IFERROR(INDEX('Budget Plan'!$D$21:$O$21,MATCH(Dashboard!$C$3,'Budget Plan'!$D$6:$O$6,0)),0)) | E12: =IF($C12="","",SUMIFS(Transactions!$F$7:$F$1006,Transactions!$D$7:$D$1006,"Expense",Transactions!$E$7:$E$1006,$C12,Transactions!$I$7:$I$1006,Dashboard!$C$3)) | F12: =IF($C12="","",D12-E12) | G12: =IF($C12="","",IF(D12=0,IF(E12>0,1,0),E12/D12)) | I12: =IFERROR(INDEX($C$12:$C$41,MATCH(LARGE($E$12:$E$41,1),$E$12:$E$41,0)),"") | J12: =IFERROR(LARGE($E$12:$E$41,1),"")
C13: =IF(Settings!B9="","",Settings!B9) | D13: =IF($C13="","",IFERROR(INDEX('Budget Plan'!$D$22:$O$22,MATCH(Dashboard!$C$3,'Budget Plan'!$D$6:$O$6,0)),0)) | E13: =IF($C13="","",SUMIFS(Transactions!$F$7:$F$1006,Transactions!$D$7:$D$1006,"Expense",Transactions!$E$7:$E$1006,$C13,Transactions!$I$7:$I$1006,Dashboard!$C$3)) | F13: =IF($C13="","",D13-E13) | G13: =IF($C13="","",IF(D13=0,IF(E13>0,1,0),E13/D13)) | I13: =IFERROR(INDEX($C$12:$C$41,MATCH(LARGE($E$12:$E$41,2),$E$12:$E$41,0)),"") | J13: =IFERROR(LARGE($E$12:$E$41,2),"")
C14: =IF(Settings!B10="","",Settings!B10) | D14: =IF($C14="","",IFERROR(INDEX('Budget Plan'!$D$23:$O$23,MATCH(Dashboard!$C$3,'Budget Plan'!$D$6:$O$6,0)),0)) | E14: =IF($C14="","",SUMIFS(Transactions!$F$7:$F$1006,Transactions!$D$7:$D$1006,"Expense",Transactions!$E$7:$E$1006,$C14,Transactions!$I$7:$I$1006,Dashboard!$C$3)) | F14: =IF($C14="","",D14-E14) | G14: =IF($C14="","",IF(D14=0,IF(E14>0,1,0),E14/D14)) | I14: =IFERROR(INDEX($C$12:$C$41,MATCH(LARGE($E$12:$E$41,3),$E$12:$E$41,0)),"") | J14: =IFERROR(LARGE($E$12:$E$41,3),"")
C15: =IF(Settings!B11="","",Settings!B11) | D15: =IF($C15="","",IFERROR(INDEX('Budget Plan'!$D$24:$O$24,MATCH(Dashboard!$C$3,'Budget Plan'!$D$6:$O$6,0)),0)) | E15: =IF($C15="","",SUMIFS(Transactions!$F$7:$F$1006,Transactions!$D$7:$D$1006,"Expense",Transactions!$E$7:$E$1006,$C15,Transactions!$I$7:$I$1006,Dashboard!$C$3)) | F15: =IF($C15="","",D15-E15) | G15: =IF($C15="","",IF(D15=0,IF(E15>0,1,0),E15/D15)) | I15: =IFERROR(INDEX($C$12:$C$41,MATCH(LARGE($E$12:$E$41,4),$E$12:$E$41,0)),"") | J15: =IFERROR(LARGE($E$12:$E$41,4),"")
C16: =IF(Settings!B12="","",Settings!B12) | D16: =IF($C16="","",IFERROR(INDEX('Budget Plan'!$D$25:$O$25,MATCH(Dashboard!$C$3,'Budget Plan'!$D$6:$O$6,0)),0)) | E16: =IF($C16="","",SUMIFS(Transactions!$F$7:$F$1006,Transactions!$D$7:$D$1006,"Expense",Transactions!$E$7:$E$1006,$C16,Transactions!$I$7:$I$1006,Dashboard!$C$3)) | F16: =IF($C16="","",D16-E16) | G16: =IF($C16="","",IF(D16=0,IF(E16>0,1,0),E16/D16)) | I16: =IFERROR(INDEX($C$12:$C$41,MATCH(LARGE($E$12:$E$41,5),$E$12:$E$41,0)),"") | J16: =IFERROR(LARGE($E$12:$E$41,5),"")
C17: =IF(Settings!B13="","",Settings!B13) | D17: =IF($C17="","",IFERROR(INDEX('Budget Plan'!$D$26:$O$26,MATCH(Dashboard!$C$3,'Budget Plan'!$D$6:$O$6,0)),0)) | E17: =IF($C17="","",SUMIFS(Transactions!$F$7:$F$1006,Transactions!$D$7:$D$1006,"Expense",Transactions!$E$7:$E$1006,$C17,Transactions!$I$7:$I$1006,Dashboard!$C$3)) | F17: =IF($C17="","",D17-E17) | G17: =IF($C17="","",IF(D17=0,IF(E17>0,1,0),E17/D17))
C18: =IF(Settings!B14="","",Settings!B14) | D18: =IF($C18="","",IFERROR(INDEX('Budget Plan'!$D$27:$O$27,MATCH(Dashboard!$C$3,'Budget Plan'!$D$6:$O$6,0)),0)) | E18: =IF($C18="","",SUMIFS(Transactions!$F$7:$F$1006,Transactions!$D$7:$D$1006,"Expense",Transactions!$E$7:$E$1006,$C18,Transactions!$I$7:$I$1006,Dashboard!$C$3)) | F18: =IF($C18="","",D18-E18) | G18: =IF($C18="","",IF(D18=0,IF(E18>0,1,0),E18/D18)) | I18: Note: if two categories tie, the first one is shown twice – that's normal for LARGE/MATCH.
C19: =IF(Settings!B15="","",Settings!B15) | D19: =IF($C19="","",IFERROR(INDEX('Budget Plan'!$D$28:$O$28,MATCH(Dashboard!$C$3,'Budget Plan'!$D$6:$O$6,0)),0)) | E19: =IF($C19="","",SUMIFS(Transactions!$F$7:$F$1006,Transactions!$D$7:$D$1006,"Expense",Transactions!$E$7:$E$1006,$C19,Transactions!$I$7:$I$1006,Dashboard!$C$3)) | F19: =IF($C19="","",D19-E19) | G19: =IF($C19="","",IF(D19=0,IF(E19>0,1,0),E19/D19))
C20: =IF(Settings!B16="","",Settings!B16) | D20: =IF($C20="","",IFERROR(INDEX('Budget Plan'!$D$29:$O$29,MATCH(Dashboard!$C$3,'Budget Plan'!$D$6:$O$6,0)),0)) | E20: =IF($C20="","",SUMIFS(Transactions!$F$7:$F$1006,Transactions!$D$7:$D$1006,"Expense",Transactions!$E$7:$E$1006,$C20,Transactions!$I$7:$I$1006,Dashboard!$C$3)) | F20: =IF($C20="","",D20-E20) | G20: =IF($C20="","",IF(D20=0,IF(E20>0,1,0),E20/D20))
C21: =IF(Settings!B17="","",Settings!B17) | D21: =IF($C21="","",IFERROR(INDEX('Budget Plan'!$D$30:$O$30,MATCH(Dashboard!$C$3,'Budget Plan'!$D$6:$O$6,0)),0)) | E21: =IF($C21="","",SUMIFS(Transactions!$F$7:$F$1006,Transactions!$D$7:$D$1006,"Expense",Transactions!$E$7:$E$1006,$C21,Transactions!$I$7:$I$1006,Dashboard!$C$3)) | F21: =IF($C21="","",D21-E21) | G21: =IF($C21="","",IF(D21=0,IF(E21>0,1,0),E21/D21))
C22: =IF(Settings!B18="","",Settings!B18) | D22: =IF($C22="","",IFERROR(INDEX('Budget Plan'!$D$31:$O$31,MATCH(Dashboard!$C$3,'Budget Plan'!$D$6:$O$6,0)),0)) | E22: =IF($C22="","",SUMIFS(Transactions!$F$7:$F$1006,Transactions!$D$7:$D$1006,"Expense",Transactions!$E$7:$E$1006,$C22,Transactions!$I$7:$I$1006,Dashboard!$C$3)) | F22: =IF($C22="","",D22-E22) | G22: =IF($C22="","",IF(D22=0,IF(E22>0,1,0),E22/D22))
C23: =IF(Settings!B19="","",Settings!B19) | D23: =IF($C23="","",IFERROR(INDEX('Budget Plan'!$D$32:$O$32,MATCH(Dashboard!$C$3,'Budget Plan'!$D$6:$O$6,0)),0)) | E23: =IF($C23="","",SUMIFS(Transactions!$F$7:$F$1006,Transactions!$D$7:$D$1006,"Expense",Transactions!$E$7:$E$1006,$C23,Transactions!$I$7:$I$1006,Dashboard!$C$3)) | F23: =IF($C23="","",D23-E23) | G23: =IF($C23="","",IF(D23=0,IF(E23>0,1,0),E23/D23))
C24: =IF(Settings!B20="","",Settings!B20) | D24: =IF($C24="","",IFERROR(INDEX('Budget Plan'!$D$33:$O$33,MATCH(Dashboard!$C$3,'Budget Plan'!$D$6:$O$6,0)),0)) | E24: =IF($C24="","",SUMIFS(Transactions!$F$7:$F$1006,Transactions!$D$7:$D$1006,"Expense",Transactions!$E$7:$E$1006,$C24,Transactions!$I$7:$I$1006,Dashboard!$C$3)) | F24: =IF($C24="","",D24-E24) | G24: =IF($C24="","",IF(D24=0,IF(E24>0,1,0),E24/D24))
C25: =IF(Settings!B21="","",Settings!B21) | D25: =IF($C25="","",IFERROR(INDEX('Budget Plan'!$D$34:$O$34,MATCH(Dashboard!$C$3,'Budget Plan'!$D$6:$O$6,0)),0)) | E25: =IF($C25="","",SUMIFS(Transactions!$F$7:$F$1006,Transactions!$D$7:$D$1006,"Expense",Transactions!$E$7:$E$1006,$C25,Transactions!$I$7:$I$1006,Dashboard!$C$3)) | F25: =IF($C25="","",D25-E25) | G25: =IF($C25="","",IF(D25=0,IF(E25>0,1,0),E25/D25))
C26: =IF(Settings!B22="","",Settings!B22) | D26: =IF($C26="","",IFERROR(INDEX('Budget Plan'!$D$35:$O$35,MATCH(Dashboard!$C$3,'Budget Plan'!$D$6:$O$6,0)),0)) | E26: =IF($C26="","",SUMIFS(Transactions!$F$7:$F$1006,Transactions!$D$7:$D$1006,"Expense",Transactions!$E$7:$E$1006,$C26,Transactions!$I$7:$I$1006,Dashboard!$C$3)) | F26: =IF($C26="","",D26-E26) | G26: =IF($C26="","",IF(D26=0,IF(E26>0,1,0),E26/D26))
C27: =IF(Settings!B23="","",Settings!B23) | D27: =IF($C27="","",IFERROR(INDEX('Budget Plan'!$D$36:$O$36,MATCH(Dashboard!$C$3,'Budget Plan'!$D$6:$O$6,0)),0)) | E27: =IF($C27="","",SUMIFS(Transactions!$F$7:$F$1006,Transactions!$D$7:$D$1006,"Expense",Transactions!$E$7:$E$1006,$C27,Transactions!$I$7:$I$1006,Dashboard!$C$3)) | F27: =IF($C27="","",D27-E27) | G27: =IF($C27="","",IF(D27=0,IF(E27>0,1,0),E27/D27))
C28: =IF(Settings!B24="","",Settings!B24) | D28: =IF($C28="","",IFERROR(INDEX('Budget Plan'!$D$37:$O$37,MATCH(Dashboard!$C$3,'Budget Plan'!$D$6:$O$6,0)),0)) | E28: =IF($C28="","",SUMIFS(Transactions!$F$7:$F$1006,Transactions!$D$7:$D$1006,"Expense",Transactions!$E$7:$E$1006,$C28,Transactions!$I$7:$I$1006,Dashboard!$C$3)) | F28: =IF($C28="","",D28-E28) | G28: =IF($C28="","",IF(D28=0,IF(E28>0,1,0),E28/D28))
C29: =IF(Settings!B25="","",Settings!B25) | D29: =IF($C29="","",IFERROR(INDEX('Budget Plan'!$D$38:$O$38,MATCH(Dashboard!$C$3,'Budget Plan'!$D$6:$O$6,0)),0)) | E29: =IF($C29="","",SUMIFS(Transactions!$F$7:$F$1006,Transactions!$D$7:$D$1006,"Expense",Transactions!$E$7:$E$1006,$C29,Transactions!$I$7:$I$1006,Dashboard!$C$3)) | F29: =IF($C29="","",D29-E29) | G29: =IF($C29="","",IF(D29=0,IF(E29>0,1,0),E29/D29))
C30: =IF(Settings!B26="","",Settings!B26) | D30: =IF($C30="","",IFERROR(INDEX('Budget Plan'!$D$39:$O$39,MATCH(Dashboard!$C$3,'Budget Plan'!$D$6:$O$6,0)),0)) | E30: =IF($C30="","",SUMIFS(Transactions!$F$7:$F$1006,Transactions!$D$7:$D$1006,"Expense",Transactions!$E$7:$E$1006,$C30,Transactions!$I$7:$I$1006,Dashboard!$C$3)) | F30: =IF($C30="","",D30-E30) | G30: =IF($C30="","",IF(D30=0,IF(E30>0,1,0),E30/D30))
C31: =IF(Settings!B27="","",Settings!B27) | D31: =IF($C31="","",IFERROR(INDEX('Budget Plan'!$D$40:$O$40,MATCH(Dashboard!$C$3,'Budget Plan'!$D$6:$O$6,0)),0)) | E31: =IF($C31="","",SUMIFS(Transactions!$F$7:$F$1006,Transactions!$D$7:$D$1006,"Expense",Transactions!$E$7:$E$1006,$C31,Transactions!$I$7:$I$1006,Dashboard!$C$3)) | F31: =IF($C31="","",D31-E31) | G31: =IF($C31="","",IF(D31=0,IF(E31>0,1,0),E31/D31))
C32: =IF(Settings!B28="","",Settings!B28) | D32: =IF($C32="","",IFERROR(INDEX('Budget Plan'!$D$41:$O$41,MATCH(Dashboard!$C$3,'Budget Plan'!$D$6:$O$6,0)),0)) | E32: =IF($C32="","",SUMIFS(Transactions!$F$7:$F$1006,Transactions!$D$7:$D$1006,"Expense",Transactions!$E$7:$E$1006,$C32,Transactions!$I$7:$I$1006,Dashboard!$C$3)) | F32: =IF($C32="","",D32-E32) | G32: =IF($C32="","",IF(D32=0,IF(E32>0,1,0),E32/D32))
C33: =IF(Settings!B29="","",Settings!B29) | D33: =IF($C33="","",IFERROR(INDEX('Budget Plan'!$D$42:$O$42,MATCH(Dashboard!$C$3,'Budget Plan'!$D$6:$O$6,0)),0)) | E33: =IF($C33="","",SUMIFS(Transactions!$F$7:$F$1006,Transactions!$D$7:$D$1006,"Expense",Transactions!$E$7:$E$1006,$C33,Transactions!$I$7:$I$1006,Dashboard!$C$3)) | F33: =IF($C33="","",D33-E33) | G33: =IF($C33="","",IF(D33=0,IF(E33>0,1,0),E33/D33))
C34: =IF(Settings!B30="","",Settings!B30) | D34: =IF($C34="","",IFERROR(INDEX('Budget Plan'!$D$43:$O$43,MATCH(Dashboard!$C$3,'Budget Plan'!$D$6:$O$6,0)),0)) | E34: =IF($C34="","",SUMIFS(Transactions!$F$7:$F$1006,Transactions!$D$7:$D$1006,"Expense",Transactions!$E$7:$E$1006,$C34,Transactions!$I$7:$I$1006,Dashboard!$C$3)) | F34: =IF($C34="","",D34-E34) | G34: =IF($C34="","",IF(D34=0,IF(E34>0,1,0),E34/D34))
C35: =IF(Settings!B31="","",Settings!B31) | D35: =IF($C35="","",IFERROR(INDEX('Budget Plan'!$D$44:$O$44,MATCH(Dashboard!$C$3,'Budget Plan'!$D$6:$O$6,0)),0)) | E35: =IF($C35="","",SUMIFS(Transactions!$F$7:$F$1006,Transactions!$D$7:$D$1006,"Expense",Transactions!$E$7:$E$1006,$C35,Transactions!$I$7:$I$1006,Dashboard!$C$3)) | F35: =IF($C35="","",D35-E35) | G35: =IF($C35="","",IF(D35=0,IF(E35>0,1,0),E35/D35))
C36: =IF(Settings!B32="","",Settings!B32) | D36: =IF($C36="","",IFERROR(INDEX('Budget Plan'!$D$45:$O$45,MATCH(Dashboard!$C$3,'Budget Plan'!$D$6:$O$6,0)),0)) | E36: =IF($C36="","",SUMIFS(Transactions!$F$7:$F$1006,Transactions!$D$7:$D$1006,"Expense",Transactions!$E$7:$E$1006,$C36,Transactions!$I$7:$I$1006,Dashboard!$C$3)) | F36: =IF($C36="","",D36-E36) | G36: =IF($C36="","",IF(D36=0,IF(E36>0,1,0),E36/D36))
C37: =IF(Settings!B33="","",Settings!B33) | D37: =IF($C37="","",IFERROR(INDEX('Budget Plan'!$D$46:$O$46,MATCH(Dashboard!$C$3,'Budget Plan'!$D$6:$O$6,0)),0)) | E37: =IF($C37="","",SUMIFS(Transactions!$F$7:$F$1006,Transactions!$D$7:$D$1006,"Expense",Transactions!$E$7:$E$1006,$C37,Transactions!$I$7:$I$1006,Dashboard!$C$3)) | F37: =IF($C37="","",D37-E37) | G37: =IF($C37="","",IF(D37=0,IF(E37>0,1,0),E37/D37))
C38: =IF(Settings!B34="","",Settings!B34) | D38: =IF($C38="","",IFERROR(INDEX('Budget Plan'!$D$47:$O$47,MATCH(Dashboard!$C$3,'Budget Plan'!$D$6:$O$6,0)),0)) | E38: =IF($C38="","",SUMIFS(Transactions!$F$7:$F$1006,Transactions!$D$7:$D$1006,"Expense",Transactions!$E$7:$E$1006,$C38,Transactions!$I$7:$I$1006,Dashboard!$C$3)) | F38: =IF($C38="","",D38-E38) | G38: =IF($C38="","",IF(D38=0,IF(E38>0,1,0),E38/D38))
C39: =IF(Settings!B35="","",Settings!B35) | D39: =IF($C39="","",IFERROR(INDEX('Budget Plan'!$D$48:$O$48,MATCH(Dashboard!$C$3,'Budget Plan'!$D$6:$O$6,0)),0)) | E39: =IF($C39="","",SUMIFS(Transactions!$F$7:$F$1006,Transactions!$D$7:$D$1006,"Expense",Transactions!$E$7:$E$1006,$C39,Transactions!$I$7:$I$1006,Dashboard!$C$3)) | F39: =IF($C39="","",D39-E39) | G39: =IF($C39="","",IF(D39=0,IF(E39>0,1,0),E39/D39))
C40: =IF(Settings!B36="","",Settings!B36) | D40: =IF($C40="","",IFERROR(INDEX('Budget Plan'!$D$49:$O$49,MATCH(Dashboard!$C$3,'Budget Plan'!$D$6:$O$6,0)),0)) | E40: =IF($C40="","",SUMIFS(Transactions!$F$7:$F$1006,Transactions!$D$7:$D$1006,"Expense",Transactions!$E$7:$E$1006,$C40,Transactions!$I$7:$I$1006,Dashboard!$C$3)) | F40: =IF($C40="","",D40-E40) | G40: =IF($C40="","",IF(D40=0,IF(E40>0,1,0),E40/D40))
C41: =IF(Settings!B37="","",Settings!B37) | D41: =IF($C41="","",IFERROR(INDEX('Budget Plan'!$D$50:$O$50,MATCH(Dashboard!$C$3,'Budget Plan'!$D$6:$O$6,0)),0)) | E41: =IF($C41="","",SUMIFS(Transactions!$F$7:$F$1006,Transactions!$D$7:$D$1006,"Expense",Transactions!$E$7:$E$1006,$C41,Transactions!$I$7:$I$1006,Dashboard!$C$3)) | F41: =IF($C41="","",D41-E41) | G41: =IF($C41="","",IF(D41=0,IF(E41>0,1,0),E41/D41))
C42: Total | D42: =SUM(D12:D41) | E42: =SUM(E12:E41) | F42: =SUM(F12:F41) | G42: =IF(D42=0,0,E42/D42)

Sheet Monthly Budget
B2: Monthly Budget
B3: Selected month (change it on the Dashboard): | E3: =Dashboard!$C$3
B5: Income | C5: Planned | D5: Actual | E5: Difference
B6: =IF(Settings!D8="","",Settings!D8) | C6: =IF($B6="","",IFERROR(INDEX('Budget Plan'!$D$8:$O$8,MATCH(Dashboard!$C$3,'Budget Plan'!$D$6:$O$6,0)),0)) | D6: =IF($B6="","",SUMIFS(Transactions!$F$7:$F$1006,Transactions!$D$7:$D$1006,"Income",Transactions!$E$7:$E$1006,$B6,Transactions!$I$7:$I$1006,Dashboard!$C$3)) | E6: =IF($B6="","",D6-C6)
B7: =IF(Settings!D9="","",Settings!D9) | C7: =IF($B7="","",IFERROR(INDEX('Budget Plan'!$D$9:$O$9,MATCH(Dashboard!$C$3,'Budget Plan'!$D$6:$O$6,0)),0)) | D7: =IF($B7="","",SUMIFS(Transactions!$F$7:$F$1006,Transactions!$D$7:$D$1006,"Income",Transactions!$E$7:$E$1006,$B7,Transactions!$I$7:$I$1006,Dashboard!$C$3)) | E7: =IF($B7="","",D7-C7)
B8: =IF(Settings!D10="","",Settings!D10) | C8: =IF($B8="","",IFERROR(INDEX('Budget Plan'!$D$10:$O$10,MATCH(Dashboard!$C$3,'Budget Plan'!$D$6:$O$6,0)),0)) | D8: =IF($B8="","",SUMIFS(Transactions!$F$7:$F$1006,Transactions!$D$7:$D$1006,"Income",Transactions!$E$7:$E$1006,$B8,Transactions!$I$7:$I$1006,Dashboard!$C$3)) | E8: =IF($B8="","",D8-C8)
B9: =IF(Settings!D11="","",Settings!D11) | C9: =IF($B9="","",IFERROR(INDEX('Budget Plan'!$D$11:$O$11,MATCH(Dashboard!$C$3,'Budget Plan'!$D$6:$O$6,0)),0)) | D9: =IF($B9="","",SUMIFS(Transactions!$F$7:$F$1006,Transactions!$D$7:$D$1006,"Income",Transactions!$E$7:$E$1006,$B9,Transactions!$I$7:$I$1006,Dashboard!$C$3)) | E9: =IF($B9="","",D9-C9)
B10: =IF(Settings!D12="","",Settings!D12) | C10: =IF($B10="","",IFERROR(INDEX('Budget Plan'!$D$12:$O$12,MATCH(Dashboard!$C$3,'Budget Plan'!$D$6:$O$6,0)),0)) | D10: =IF($B10="","",SUMIFS(Transactions!$F$7:$F$1006,Transactions!$D$7:$D$1006,"Income",Transactions!$E$7:$E$1006,$B10,Transactions!$I$7:$I$1006,Dashboard!$C$3)) | E10: =IF($B10="","",D10-C10)
B11: =IF(Settings!D13="","",Settings!D13) | C11: =IF($B11="","",IFERROR(INDEX('Budget Plan'!$D$13:$O$13,MATCH(Dashboard!$C$3,'Budget Plan'!$D$6:$O$6,0)),0)) | D11: =IF($B11="","",SUMIFS(Transactions!$F$7:$F$1006,Transactions!$D$7:$D$1006,"Income",Transactions!$E$7:$E$1006,$B11,Transactions!$I$7:$I$1006,Dashboard!$C$3)) | E11: =IF($B11="","",D11-C11)
B12: =IF(Settings!D14="","",Settings!D14) | C12: =IF($B12="","",IFERROR(INDEX('Budget Plan'!$D$14:$O$14,MATCH(Dashboard!$C$3,'Budget Plan'!$D$6:$O$6,0)),0)) | D12: =IF($B12="","",SUMIFS(Transactions!$F$7:$F$1006,Transactions!$D$7:$D$1006,"Income",Transactions!$E$7:$E$1006,$B12,Transactions!$I$7:$I$1006,Dashboard!$C$3)) | E12: =IF($B12="","",D12-C12)
B13: =IF(Settings!D15="","",Settings!D15) | C13: =IF($B13="","",IFERROR(INDEX('Budget Plan'!$D$15:$O$15,MATCH(Dashboard!$C$3,'Budget Plan'!$D$6:$O$6,0)),0)) | D13: =IF($B13="","",SUMIFS(Transactions!$F$7:$F$1006,Transactions!$D$7:$D$1006,"Income",Transactions!$E$7:$E$1006,$B13,Transactions!$I$7:$I$1006,Dashboard!$C$3)) | E13: =IF($B13="","",D13-C13)
B14: =IF(Settings!D16="","",Settings!D16) | C14: =IF($B14="","",IFERROR(INDEX('Budget Plan'!$D$16:$O$16,MATCH(Dashboard!$C$3,'Budget Plan'!$D$6:$O$6,0)),0)) | D14: =IF($B14="","",SUMIFS(Transactions!$F$7:$F$1006,Transactions!$D$7:$D$1006,"Income",Transactions!$E$7:$E$1006,$B14,Transactions!$I$7:$I$1006,Dashboard!$C$3)) | E14: =IF($B14="","",D14-C14)
B15: =IF(Settings!D17="","",Settings!D17) | C15: =IF($B15="","",IFERROR(INDEX('Budget Plan'!$D$17:$O$17,MATCH(Dashboard!$C$3,'Budget Plan'!$D$6:$O$6,0)),0)) | D15: =IF($B15="","",SUMIFS(Transactions!$F$7:$F$1006,Transactions!$D$7:$D$1006,"Income",Transactions!$E$7:$E$1006,$B15,Transactions!$I$7:$I$1006,Dashboard!$C$3)) | E15: =IF($B15="","",D15-C15)
B16: Total income | C16: =SUM(C6:C15) | D16: =SUM(D6:D15) | E16: =SUM(E6:E15)
B18: Expenses | C18: Planned | D18: Actual | E18: Left to spend | F18: % used
B19: =Dashboard!C12 | C19: =Dashboard!D12 | D19: =Dashboard!E12 | E19: =Dashboard!F12 | F19: =Dashboard!G12
B20: =Dashboard!C13 | C20: =Dashboard!D13 | D20: =Dashboard!E13 | E20: =Dashboard!F13 | F20: =Dashboard!G13
B21: =Dashboard!C14 | C21: =Dashboard!D14 | D21: =Dashboard!E14 | E21: =Dashboard!F14 | F21: =Dashboard!G14
B22: =Dashboard!C15 | C22: =Dashboard!D15 | D22: =Dashboard!E15 | E22: =Dashboard!F15 | F22: =Dashboard!G15
B23: =Dashboard!C16 | C23: =Dashboard!D16 | D23: =Dashboard!E16 | E23: =Dashboard!F16 | F23: =Dashboard!G16
B24: =Dashboard!C17 | C24: =Dashboard!D17 | D24: =Dashboard!E17 | E24: =Dashboard!F17 | F24: =Dashboard!G17
B25: =Dashboard!C18 | C25: =Dashboard!D18 | D25: =Dashboard!E18 | E25: =Dashboard!F18 | F25: =Dashboard!G18
B26: =Dashboard!C19 | C26: =Dashboard!D19 | D26: =Dashboard!E19 | E26: =Dashboard!F19 | F26: =Dashboard!G19
B27: =Dashboard!C20 | C27: =Dashboard!D20 | D27: =Dashboard!E20 | E27: =Dashboard!F20 | F27: =Dashboard!G20
B28: =Dashboard!C21 | C28: =Dashboard!D21 | D28: =Dashboard!E21 | E28: =Dashboard!F21 | F28: =Dashboard!G21
B29: =Dashboard!C22 | C29: =Dashboard!D22 | D29: =Dashboard!E22 | E29: =Dashboard!F22 | F29: =Dashboard!G22
B30: =Dashboard!C23 | C30: =Dashboard!D23 | D30: =Dashboard!E23 | E30: =Dashboard!F23 | F30: =Dashboard!G23
... B48: =Dashboard!C41 | C48: =Dashboard!D41 | D48: =Dashboard!E41 | E48: =Dashboard!F41 | F48: =Dashboard!G41
B49: Total expenses | C49: =SUM(C19:C48) | D49: =SUM(D19:D48) | E49: =SUM(E19:E48) | F49: =IF(C49=0,0,D49/C49)
B51: Left over (actual) | D51: =D16-D49
B52: Left over (planned) | D52: =C16-C49

Sheet Settings
B2: Settings
B3: Edit these lists once. Every dropdown in the workbook updates automatically.
B5: Budget year | C5: 2026 | D5: ← change the year and every month in the workbook follows
B7: Expense categories | D7: Income categories | F7: Accounts | H7: Months (auto) | J7: All categories (auto)
B8: Housing | D8: Salary | F8: Checking | H8: =DATE($C$5,1,1) | J8: =IF(B8="","",B8)
B9: Utilities | D9: Partner salary | F9: Savings | H9: =DATE($C$5,2,1) | J9: =IF(B9="","",B9)
B10: Groceries | D10: Side income | F10: Credit card | H10: =DATE($C$5,3,1) | J10: =IF(B10="","",B10)
B11: Eating out | D11: Refunds | F11: Cash | H11: =DATE($C$5,4,1) | J11: =IF(B11="","",B11)
B12: Transport | D12: Other income | H12: =DATE($C$5,5,1) | J12: =IF(B12="","",B12)
B13: Insurance | H13: =DATE($C$5,6,1) | J13: =IF(B13="","",B13)
B14: Health | H14: =DATE($C$5,7,1) | J14: =IF(B14="","",B14)
B15: Subscriptions | H15: =DATE($C$5,8,1) | J15: =IF(B15="","",B15)
B16: Phone & internet | H16: =DATE($C$5,9,1) | J16: =IF(B16="","",B16)
B17: Shopping | H17: =DATE($C$5,10,1) | J17: =IF(B17="","",B17)
B18: Personal care | H18: =DATE($C$5,11,1) | J18: =IF(B18="","",B18)
B19: Kids & family | H19: =DATE($C$5,12,1) | J19: =IF(B19="","",B19)
B20: Pets | J20: =IF(B20="","",B20)
B21: Gifts & giving | J21: =IF(B21="","",B21)
B22: Fun & hobbies | J22: =IF(B22="","",B22)
B23: Travel | J23: =IF(B23="","",B23)
B24: Education | J24: =IF(B24="","",B24)
B25: Debt payments | J25: =IF(B25="","",B25)
B26: Savings transfers | J26: =IF(B26="","",B26)
B27: Other | J27: =IF(B27="","",B27)
J28: =IF(B28="","",B28)
J29: =IF(B29="","",B29)
J30: =IF(B30="","",B30)
J31: =IF(B31="","",B31)
J32: =IF(B32="","",B32)
J33: =IF(B33="","",B33)
J34: =IF(B34="","",B34)
J35: =IF(B35="","",B35)
J36: =IF(B36="","",B36)
J37: =IF(B37="","",B37)
J38: =IF(D8="","",D8)
J39: =IF(D9="","",D9)
B40: Tip: keep category names short. If you rename a category, also update it in Transactions and Budget Plan (Find & Replace). | J40: =IF(D10="","",D10)
J41: =IF(D11="","",D11)
J42: =IF(D12="","",D12)
J43: =IF(D13="","",D13)
J44: =IF(D14="","",D14)
J45: =IF(D15="","",D15)
J46: =IF(D16="","",D16)
J47: =IF(D17="","",D17)
J48: =IF(D18="","",D18)
J49: =IF(D19="","",D19)
J50: =IF(D20="","",D20)
J51: =IF(D21="","",D21)
J52: =IF(D22="","",D22)
... J67: =IF(D37="","",D37)

Sheet Transactions
B2: Transactions
B3: Log every income and expense here. Yellow cells are yours to fill; the rest is automatic.
B6: Date | C6: Description | D6: Type | E6: Category | F6: Amount | G6: Account | H6: Notes | I6: Month (auto)
B7: 46266 | C7: Paycheck | D7: Income | E7: Salary | F7: 3200 | G7: Checking | H7: example row – delete me | I7: =IF(B7="","",DATE(YEAR(B7),MONTH(B7),1))
B8: 46266 | C8: Rent | D8: Expense | E8: Housing | F8: 1450 | G8: Checking | H8: example | I8: =IF(B8="","",DATE(YEAR(B8),MONTH(B8),1))
B9: 46268 | C9: Grocery run | D9: Expense | E9: Groceries | F9: 128.4 | G9: Credit card | H9: example | I9: =IF(B9="","",DATE(YEAR(B9),MONTH(B9),1))
B10: 46269 | C10: Electric bill | D10: Expense | E10: Utilities | F10: 96.1 | G10: Checking | H10: example | I10: =IF(B10="","",DATE(YEAR(B10),MONTH(B10),1))
B11: 46271 | C11: Gas | D11: Expense | E11: Transport | F11: 52 | G11: Credit card | H11: example | I11: =IF(B11="","",DATE(YEAR(B11),MONTH(B11),1))
B12: 46272 | C12: Streaming | D12: Expense | E12: Subscriptions | F12: 15.99 | G12: Credit card | H12: example | I12: =IF(B12="","",DATE(YEAR(B12),MONTH(B12),1))
B13: 46274 | C13: Dinner out | D13: Expense | E13: Eating out | F13: 64.3 | G13: Credit card | H13: example | I13: =IF(B13="","",DATE(YEAR(B13),MONTH(B13),1))
B14: 46277 | C14: Freelance invoice | D14: Income | E14: Side income | F14: 450 | G14: Checking | H14: example | I14: =IF(B14="","",DATE(YEAR(B14),MONTH(B14),1))
B15: 46279 | C15: Grocery run | D15: Expense | E15: Groceries | F15: 142.75 | G15: Credit card | H15: example | I15: =IF(B15="","",DATE(YEAR(B15),MONTH(B15),1))
B16: 46280 | C16: Paycheck | D16: Income | E16: Salary | F16: 3200 | G16: Checking | H16: example | I16: =IF(B16="","",DATE(YEAR(B16),MONTH(B16),1))
B17: 46281 | C17: Phone plan | D17: Expense | E17: Phone & internet | F17: 70 | G17: Checking | H17: example | I17: =IF(B17="","",DATE(YEAR(B17),MONTH(B17),1))
B18: 46283 | C18: Transfer to savings | D18: Expense | E18: Savings transfers | F18: 400 | G18: Savings | H18: example | I18: =IF(B18="","",DATE(YEAR(B18),MONTH(B18),1))
... B35: 46295 | C35: Credit card payment | D35: Expense | E35: Debt payments | F35: 250 | G35: Checking | H35: example | I35: =IF(B35="","",DATE(YEAR(B35),MONTH(B35),1))
I36: =IF(B36="","",DATE(YEAR(B36),MONTH(B36),1))
I37: =IF(B37="","",DATE(YEAR(B37),MONTH(B37),1))
I38: =IF(B38="","",DATE(YEAR(B38),MONTH(B38),1))
I39: =IF(B39="","",DATE(YEAR(B39),MONTH(B39),1))
I40: =IF(B40="","",DATE(YEAR(B40),MONTH(B40),1))
I41: =IF(B41="","",DATE(YEAR(B41),MONTH(B41),1))
I42: =IF(B42="","",DATE(YEAR(B42),MONTH(B42),1))
I43: =IF(B43="","",DATE(YEAR(B43),MONTH(B43),1))
I44: =IF(B44="","",DATE(YEAR(B44),MONTH(B44),1))
I45: =IF(B45="","",DATE(YEAR(B45),MONTH(B45),1))
I46: =IF(B46="","",DATE(YEAR(B46),MONTH(B46),1))
I47: =IF(B47="","",DATE(YEAR(B47),MONTH(B47),1))
... I1006: =IF(B1006="","",DATE(YEAR(B1006),MONTH(B1006),1))

Sheet Budget Plan
B2: Budget Plan
B3: Type a default monthly amount per category. Every month copies the default — overwrite any single month to change it.
B6: Category | C6: Default / month | D6: =Settings!$H$8 | E6: =Settings!$H$9 | F6: =Settings!$H$10 | G6: =Settings!$H$11 | H6: =Settings!$H$12 | I6: =Settings!$H$13 | J6: =Settings!$H$14 | K6: =Settings!$H$15 | L6: =Settings!$H$16 | M6: =Settings!$H$17 | N6: =Settings!$H$18 | O6: =Settings!$H$19
B7: INCOME
B8: =IF(Settings!D8="","",Settings!D8) | C8: 6400 | D8: =$C8 | E8: =$C8 | F8: =$C8 | G8: =$C8 | H8: =$C8 | I8: =$C8 | J8: =$C8 | K8: =$C8 | ... O8: =$C8
B9: =IF(Settings!D9="","",Settings!D9) | D9: =$C9 | E9: =$C9 | F9: =$C9 | G9: =$C9 | H9: =$C9 | I9: =$C9 | J9: =$C9 | K9: =$C9 | ... O9: =$C9
B10: =IF(Settings!D10="","",Settings!D10) | C10: 450 | D10: =$C10 | E10: =$C10 | F10: =$C10 | G10: =$C10 | H10: =$C10 | I10: =$C10 | J10: =$C10 | K10: =$C10 | ... O10: =$C10
B11: =IF(Settings!D11="","",Settings!D11) | D11: =$C11 | E11: =$C11 | F11: =$C11 | G11: =$C11 | H11: =$C11 | I11: =$C11 | J11: =$C11 | K11: =$C11 | ... O11: =$C11
B12: =IF(Settings!D12="","",Settings!D12) | D12: =$C12 | E12: =$C12 | F12: =$C12 | G12: =$C12 | H12: =$C12 | I12: =$C12 | J12: =$C12 | K12: =$C12 | ... O12: =$C12
B13: =IF(Settings!D13="","",Settings!D13) | D13: =$C13 | E13: =$C13 | F13: =$C13 | G13: =$C13 | H13: =$C13 | I13: =$C13 | J13: =$C13 | K13: =$C13 | ... O13: =$C13
B14: =IF(Settings!D14="","",Settings!D14) | D14: =$C14 | E14: =$C14 | F14: =$C14 | G14: =$C14 | H14: =$C14 | I14: =$C14 | J14: =$C14 | K14: =$C14 | ... O14: =$C14
B15: =IF(Settings!D15="","",Settings!D15) | D15: =$C15 | E15: =$C15 | F15: =$C15 | G15: =$C15 | H15: =$C15 | I15: =$C15 | J15: =$C15 | K15: =$C15 | ... O15: =$C15
B16: =IF(Settings!D16="","",Settings!D16) | D16: =$C16 | E16: =$C16 | F16: =$C16 | G16: =$C16 | H16: =$C16 | I16: =$C16 | J16: =$C16 | K16: =$C16 | ... O16: =$C16
B17: =IF(Settings!D17="","",Settings!D17) | D17: =$C17 | E17: =$C17 | F17: =$C17 | G17: =$C17 | H17: =$C17 | I17: =$C17 | J17: =$C17 | K17: =$C17 | ... O17: =$C17
B18: Total planned income | C18: =SUM(C8:C17) | D18: =SUM(D8:D17) | E18: =SUM(E8:E17) | F18: =SUM(F8:F17) | G18: =SUM(G8:G17) | H18: =SUM(H8:H17) | I18: =SUM(I8:I17) | J18: =SUM(J8:J17) | ... O18: =SUM(O8:O17)
B20: EXPENSES
B21: =IF(Settings!B8="","",Settings!B8) | C21: 1450 | D21: =$C21 | E21: =$C21 | F21: =$C21 | G21: =$C21 | H21: =$C21 | I21: =$C21 | J21: =$C21 | K21: =$C21 | ... O21: =$C21
B22: =IF(Settings!B9="","",Settings!B9) | C22: 120 | D22: =$C22 | E22: =$C22 | F22: =$C22 | G22: =$C22 | H22: =$C22 | I22: =$C22 | J22: =$C22 | K22: =$C22 | ... O22: =$C22
B23: =IF(Settings!B10="","",Settings!B10) | C23: 550 | D23: =$C23 | E23: =$C23 | F23: =$C23 | G23: =$C23 | H23: =$C23 | I23: =$C23 | J23: =$C23 | K23: =$C23 | ... O23: =$C23
B24: =IF(Settings!B11="","",Settings!B11) | C24: 200 | D24: =$C24 | E24: =$C24 | F24: =$C24 | G24: =$C24 | H24: =$C24 | I24: =$C24 | J24: =$C24 | K24: =$C24 | ... O24: =$C24
B25: =IF(Settings!B12="","",Settings!B12) | C25: 220 | D25: =$C25 | E25: =$C25 | F25: =$C25 | G25: =$C25 | H25: =$C25 | I25: =$C25 | J25: =$C25 | K25: =$C25 | ... O25: =$C25
B26: =IF(Settings!B13="","",Settings!B13) | C26: 130 | D26: =$C26 | E26: =$C26 | F26: =$C26 | G26: =$C26 | H26: =$C26 | I26: =$C26 | J26: =$C26 | K26: =$C26 | ... O26: =$C26
B27: =IF(Settings!B14="","",Settings!B14) | C27: 60 | D27: =$C27 | E27: =$C27 | F27: =$C27 | G27: =$C27 | H27: =$C27 | I27: =$C27 | J27: =$C27 | K27: =$C27 | ... O27: =$C27
B28: =IF(Settings!B15="","",Settings!B15) | C28: 45 | D28: =$C28 | E28: =$C28 | F28: =$C28 | G28: =$C28 | H28: =$C28 | I28: =$C28 | J28: =$C28 | K28: =$C28 | ... O28: =$C28
B29: =IF(Settings!B16="","",Settings!B16) | C29: 90 | D29: =$C29 | E29: =$C29 | F29: =$C29 | G29: =$C29 | H29: =$C29 | I29: =$C29 | J29: =$C29 | K29: =$C29 | ... O29: =$C29
B30: =IF(Settings!B17="","",Settings!B17) | C30: 150 | D30: =$C30 | E30: =$C30 | F30: =$C30 | G30: =$C30 | H30: =$C30 | I30: =$C30 | J30: =$C30 | K30: =$C30 | ... O30: =$C30
B31: =IF(Settings!B18="","",Settings!B18) | C31: 40 | D31: =$C31 | E31: =$C31 | F31: =$C31 | G31: =$C31 | H31: =$C31 | I31: =$C31 | J31: =$C31 | K31: =$C31 | ... O31: =$C31
B32: =IF(Settings!B19="","",Settings!B19) | D32: =$C32 | E32: =$C32 | F32: =$C32 | G32: =$C32 | H32: =$C32 | I32: =$C32 | J32: =$C32 | K32: =$C32 | ... O32: =$C32
B33: =IF(Settings!B20="","",Settings!B20) | D33: =$C33 | E33: =$C33 | F33: =$C33 | G33: =$C33 | H33: =$C33 | I33: =$C33 | J33: =$C33 | K33: =$C33 | ... O33: =$C33
B34: =IF(Settings!B21="","",Settings!B21) | C34: 50 | D34: =$C34 | E34: =$C34 | F34: =$C34 | G34: =$C34 | H34: =$C34 | I34: =$C34 | J34: =$C34 | K34: =$C34 | ... O34: =$C34
B35: =IF(Settings!B22="","",Settings!B22) | C35: 120 | D35: =$C35 | E35: =$C35 | F35: =$C35 | G35: =$C35 | H35: =$C35 | I35: =$C35 | J35: =$C35 | K35: =$C35 | ... O35: =$C35
B36: =IF(Settings!B23="","",Settings!B23) | C36: 150 | D36: =$C36 | E36: =$C36 | F36: =$C36 | G36: =$C36 | H36: =$C36 | I36: =$C36 | J36: =$C36 | K36: =$C36 | ... O36: =$C36
B37: =IF(Settings!B24="","",Settings!B24) | D37: =$C37 | E37: =$C37 | F37: =$C37 | G37: =$C37 | H37: =$C37 | I37: =$C37 | J37: =$C37 | K37: =$C37 | ... O37: =$C37
B38: =IF(Settings!B25="","",Settings!B25) | D38: =$C38 | E38: =$C38 | F38: =$C38 | G38: =$C38 | H38: =$C38 | I38: =$C38 | J38: =$C38 | K38: =$C38 | ... O38: =$C38
B39: =IF(Settings!B26="","",Settings!B26) | C39: 800 | D39: =$C39 | E39: =$C39 | F39: =$C39 | G39: =$C39 | H39: =$C39 | I39: =$C39 | J39: =$C39 | K39: =$C39 | ... O39: =$C39
B40: =IF(Settings!B27="","",Settings!B27) | C40: 75 | D40: =$C40 | E40: =$C40 | F40: =$C40 | G40: =$C40 | H40: =$C40 | I40: =$C40 | J40: =$C40 | K40: =$C40 | ... O40: =$C40
B41: =IF(Settings!B28="","",Settings!B28) | D41: =$C41 | E41: =$C41 | F41: =$C41 | G41: =$C41 | H41: =$C41 | I41: =$C41 | J41: =$C41 | K41: =$C41 | ... O41: =$C41
B42: =IF(Settings!B29="","",Settings!B29) | D42: =$C42 | E42: =$C42 | F42: =$C42 | G42: =$C42 | H42: =$C42 | I42: =$C42 | J42: =$C42 | K42: =$C42 | ... O42: =$C42
B43: =IF(Settings!B30="","",Settings!B30) | D43: =$C43 | E43: =$C43 | F43: =$C43 | G43: =$C43 | H43: =$C43 | I43: =$C43 | J43: =$C43 | K43: =$C43 | ... O43: =$C43
B44: =IF(Settings!B31="","",Settings!B31) | D44: =$C44 | E44: =$C44 | F44: =$C44 | G44: =$C44 | H44: =$C44 | I44: =$C44 | J44: =$C44 | K44: =$C44 | ... O44: =$C44
B45: =IF(Settings!B32="","",Settings!B32) | D45: =$C45 | E45: =$C45 | F45: =$C45 | G45: =$C45 | H45: =$C45 | I45: =$C45 | J45: =$C45 | K45: =$C45 | ... O45: =$C45
B46: =IF(Settings!B33="","",Settings!B33) | D46: =$C46 | E46: =$C46 | F46: =$C46 | G46: =$C46 | H46: =$C46 | I46: =$C46 | J46: =$C46 | K46: =$C46 | ... O46: =$C46
B47: =IF(Settings!B34="","",Settings!B34) | D47: =$C47 | E47: =$C47 | F47: =$C47 | G47: =$C47 | H47: =$C47 | I47: =$C47 | J47: =$C47 | K47: =$C47 | ... O47: =$C47
B48: =IF(Settings!B35="","",Settings!B35) | D48: =$C48 | E48: =$C48 | F48: =$C48 | G48: =$C48 | H48: =$C48 | I48: =$C48 | J48: =$C48 | K48: =$C48 | ... O48: =$C48
B49: =IF(Settings!B36="","",Settings!B36) | D49: =$C49 | E49: =$C49 | F49: =$C49 | G49: =$C49 | H49: =$C49 | I49: =$C49 | J49: =$C49 | K49: =$C49 | ... O49: =$C49
B50: =IF(Settings!B37="","",Settings!B37) | D50: =$C50 | E50: =$C50 | F50: =$C50 | G50: =$C50 | H50: =$C50 | I50: =$C50 | J50: =$C50 | K50: =$C50 | ... O50: =$C50
B51: Total planned expenses | C51: =SUM(C21:C50) | D51: =SUM(D21:D50) | E51: =SUM(E21:E50) | F51: =SUM(F21:F50) | G51: =SUM(G21:G50) | H51: =SUM(H21:H50) | I51: =SUM(I21:I50) | J51: =SUM(J21:J50) | ... O51: =SUM(O21:O50)
B52: Planned left over | C52: =C18-C51 | D52: =D18-D51 | E52: =E18-E51 | F52: =F18-F51 | G52: =G18-G51 | H52: =H18-H51 | I52: =I18-I51 | J52: =J18-J51 | ... O52: =O18-O51
B54: Defaults above are examples – replace them with your own numbers.

Sheet Annual Overview
B2: Annual Overview
B3: Actual spending per category, every month of the year. Fully automatic.
B6: Category | C6: =Settings!$H$8 | D6: =Settings!$H$9 | E6: =Settings!$H$10 | F6: =Settings!$H$11 | G6: =Settings!$H$12 | H6: =Settings!$H$13 | I6: =Settings!$H$14 | J6: =Settings!$H$15 | K6: =Settings!$H$16 | L6: =Settings!$H$17 | M6: =Settings!$H$18 | N6: =Settings!$H$19 | O6: Year total | P6: Monthly avg
B7: INCOME
B8: =IF(Settings!D8="","",Settings!D8) | C8: =IF($B8="","",SUMIFS(Transactions!$F$7:$F$1006,Transactions!$D$7:$D$1006,"Income",Transactions!$E$7:$E$1006,$B8,Transactions!$I$7:$I$1006,C$6)) | D8: =IF($B8="","",SUMIFS(Transactions!$F$7:$F$1006,Transactions!$D$7:$D$1006,"Income",Transactions!$E$7:$E$1006,$B8,Transactions!$I$7:$I$1006,D$6)) | E8: =IF($B8="","",SUMIFS(Transactions!$F$7:$F$1006,Transactions!$D$7:$D$1006,"Income",Transactions!$E$7:$E$1006,$B8,Transactions!$I$7:$I$1006,E$6)) | F8: =IF($B8="","",SUMIFS(Transactions!$F$7:$F$1006,Transactions!$D$7:$D$1006,"Income",Transactions!$E$7:$E$1006,$B8,Transactions!$I$7:$I$1006,F$6)) | G8: =IF($B8="","",SUMIFS(Transactions!$F$7:$F$1006,Transactions!$D$7:$D$1006,"Income",Transactions!$E$7:$E$1006,$B8,Transactions!$I$7:$I$1006,G$6)) | H8: =IF($B8="","",SUMIFS(Transactions!$F$7:$F$1006,Transactions!$D$7:$D$1006,"Income",Transactions!$E$7:$E$1006,$B8,Transactions!$I$7:$I$1006,H$6)) | I8: =IF($B8="","",SUMIFS(Transactions!$F$7:$F$1006,Transactions!$D$7:$D$1006,"Income",Transactions!$E$7:$E$1006,$B8,Transactions!$I$7:$I$1006,I$6)) | J8: =IF($B8="","",SUMIFS(Transactions!$F$7:$F$1006,Transactions!$D$7:$D$1006,"Income",Transactions!$E$7:$E$1006,$B8,Transactions!$I$7:$I$1006,J$6)) | ... N8: =IF($B8="","",SUMIFS(Transactions!$F$7:$F$1006,Transactions!$D$7:$D$1006,"Income",Transactions!$E$7:$E$1006,$B8,Transactions!$I$7:$I$1006,N$6)) | O8: =IF($B8="","",SUM(C8:N8)) | P8: =IF($B8="","",IFERROR(O8/MAX(1,COUNTIF(C8:N8,">0")),0))
B9: =IF(Settings!D9="","",Settings!D9) | C9: =IF($B9="","",SUMIFS(Transactions!$F$7:$F$1006,Transactions!$D$7:$D$1006,"Income",Transactions!$E$7:$E$1006,$B9,Transactions!$I$7:$I$1006,C$6)) | D9: =IF($B9="","",SUMIFS(Transactions!$F$7:$F$1006,Transactions!$D$7:$D$1006,"Income",Transactions!$E$7:$E$1006,$B9,Transactions!$I$7:$I$1006,D$6)) | E9: =IF($B9="","",SUMIFS(Transactions!$F$7:$F$1006,Transactions!$D$7:$D$1006,"Income",Transactions!$E$7:$E$1006,$B9,Transactions!$I$7:$I$1006,E$6)) | F9: =IF($B9="","",SUMIFS(Transactions!$F$7:$F$1006,Transactions!$D$7:$D$1006,"Income",Transactions!$E$7:$E$1006,$B9,Transactions!$I$7:$I$1006,F$6)) | G9: =IF($B9="","",SUMIFS(Transactions!$F$7:$F$1006,Transactions!$D$7:$D$1006,"Income",Transactions!$E$7:$E$1006,$B9,Transactions!$I$7:$I$1006,G$6)) | H9: =IF($B9="","",SUMIFS(Transactions!$F$7:$F$1006,Transactions!$D$7:$D$1006,"Income",Transactions!$E$7:$E$1006,$B9,Transactions!$I$7:$I$1006,H$6)) | I9: =IF($B9="","",SUMIFS(Transactions!$F$7:$F$1006,Transactions!$D$7:$D$1006,"Income",Transactions!$E$7:$E$1006,$B9,Transactions!$I$7:$I$1006,I$6)) | J9: =IF($B9="","",SUMIFS(Transactions!$F$7:$F$1006,Transactions!$D$7:$D$1006,"Income",Transactions!$E$7:$E$1006,$B9,Transactions!$I$7:$I$1006,J$6)) | ... N9: =IF($B9="","",SUMIFS(Transactions!$F$7:$F$1006,Transactions!$D$7:$D$1006,"Income",Transactions!$E$7:$E$1006,$B9,Transactions!$I$7:$I$1006,N$6)) | O9: =IF($B9="","",SUM(C9:N9)) | P9: =IF($B9="","",IFERROR(O9/MAX(1,COUNTIF(C9:N9,">0")),0))
B10: =IF(Settings!D10="","",Settings!D10) | C10: =IF($B10="","",SUMIFS(Transactions!$F$7:$F$1006,Transactions!$D$7:$D$1006,"Income",Transactions!$E$7:$E$1006,$B10,Transactions!$I$7:$I$1006,C$6)) | D10: =IF($B10="","",SUMIFS(Transactions!$F$7:$F$1006,Transactions!$D$7:$D$1006,"Income",Transactions!$E$7:$E$1006,$B10,Transactions!$I$7:$I$1006,D$6)) | E10: =IF($B10="","",SUMIFS(Transactions!$F$7:$F$1006,Transactions!$D$7:$D$1006,"Income",Transactions!$E$7:$E$1006,$B10,Transactions!$I$7:$I$1006,E$6)) | F10: =IF($B10="","",SUMIFS(Transactions!$F$7:$F$1006,Transactions!$D$7:$D$1006,"Income",Transactions!$E$7:$E$1006,$B10,Transactions!$I$7:$I$1006,F$6)) | G10: =IF($B10="","",SUMIFS(Transactions!$F$7:$F$1006,Transactions!$D$7:$D$1006,"Income",Transactions!$E$7:$E$1006,$B10,Transactions!$I$7:$I$1006,G$6)) | H10: =IF($B10="","",SUMIFS(Transactions!$F$7:$F$1006,Transactions!$D$7:$D$1006,"Income",Transactions!$E$7:$E$1006,$B10,Transactions!$I$7:$I$1006,H$6)) | I10: =IF($B10="","",SUMIFS(Transactions!$F$7:$F$1006,Transactions!$D$7:$D$1006,"Income",Transactions!$E$7:$E$1006,$B10,Transactions!$I$7:$I$1006,I$6)) | J10: =IF($B10="","",SUMIFS(Transactions!$F$7:$F$1006,Transactions!$D$7:$D$1006,"Income",Transactions!$E$7:$E$1006,$B10,Transactions!$I$7:$I$1006,J$6)) | ... N10: =IF($B10="","",SUMIFS(Transactions!$F$7:$F$1006,Transactions!$D$7:$D$1006,"Income",Transactions!$E$7:$E$1006,$B10,Transactions!$I$7:$I$1006,N$6)) | O10: =IF($B10="","",SUM(C10:N10)) | P10: =IF($B10="","",IFERROR(O10/MAX(1,COUNTIF(C10:N10,">0")),0))
B11: =IF(Settings!D11="","",Settings!D11) | C11: =IF($B11="","",SUMIFS(Transactions!$F$7:$F$1006,Transactions!$D$7:$D$1006,"Income",Transactions!$E$7:$E$1006,$B11,Transactions!$I$7:$I$1006,C$6)) | D11: =IF($B11="","",SUMIFS(Transactions!$F$7:$F$1006,Transactions!$D$7:$D$1006,"Income",Transactions!$E$7:$E$1006,$B11,Transactions!$I$7:$I$1006,D$6)) | E11: =IF($B11="","",SUMIFS(Transactions!$F$7:$F$1006,Transactions!$D$7:$D$1006,"Income",Transactions!$E$7:$E$1006,$B11,Transactions!$I$7:$I$1006,E$6)) | F11: =IF($B11="","",SUMIFS(Transactions!$F$7:$F$1006,Transactions!$D$7:$D$1006,"Income",Transactions!$E$7:$E$1006,$B11,Transactions!$I$7:$I$1006,F$6)) | G11: =IF($B11="","",SUMIFS(Transactions!$F$7:$F$1006,Transactions!$D$7:$D$1006,"Income",Transactions!$E$7:$E$1006,$B11,Transactions!$I$7:$I$1006,G$6)) | H11: =IF($B11="","",SUMIFS(Transactions!$F$7:$F$1006,Transactions!$D$7:$D$1006,"Income",Transactions!$E$7:$E$1006,$B11,Transactions!$I$7:$I$1006,H$6)) | I11: =IF($B11="","",SUMIFS(Transactions!$F$7:$F$1006,Transactions!$D$7:$D$1006,"Income",Transactions!$E$7:$E$1006,$B11,Transactions!$I$7:$I$1006,I$6)) | J11: =IF($B11="","",SUMIFS(Transactions!$F$7:$F$1006,Transactions!$D$7:$D$1006,"Income",Transactions!$E$7:$E$1006,$B11,Transactions!$I$7:$I$1006,J$6)) | ... N11: =IF($B11="","",SUMIFS(Transactions!$F$7:$F$1006,Transactions!$D$7:$D$1006,"Income",Transactions!$E$7:$E$1006,$B11,Transactions!$I$7:$I$1006,N$6)) | O11: =IF($B11="","",SUM(C11:N11)) | P11: =IF($B11="","",IFERROR(O11/MAX(1,COUNTIF(C11:N11,">0")),0))
B12: =IF(Settings!D12="","",Settings!D12) | C12: =IF($B12="","",SUMIFS(Transactions!$F$7:$F$1006,Transactions!$D$7:$D$1006,"Income",Transactions!$E$7:$E$1006,$B12,Transactions!$I$7:$I$1006,C$6)) | D12: =IF($B12="","",SUMIFS(Transactions!$F$7:$F$1006,Transactions!$D$7:$D$1006,"Income",Transactions!$E$7:$E$1006,$B12,Transactions!$I$7:$I$1006,D$6)) | E12: =IF($B12="","",SUMIFS(Transactions!$F$7:$F$1006,Transactions!$D$7:$D$1006,"Income",Transactions!$E$7:$E$1006,$B12,Transactions!$I$7:$I$1006,E$6)) | F12: =IF($B12="","",SUMIFS(Transactions!$F$7:$F$1006,Transactions!$D$7:$D$1006,"Income",Transactions!$E$7:$E$1006,$B12,Transactions!$I$7:$I$1006,F$6)) | G12: =IF($B12="","",SUMIFS(Transactions!$F$7:$F$1006,Transactions!$D$7:$D$1006,"Income",Transactions!$E$7:$E$1006,$B12,Transactions!$I$7:$I$1006,G$6)) | H12: =IF($B12="","",SUMIFS(Transactions!$F$7:$F$1006,Transactions!$D$7:$D$1006,"Income",Transactions!$E$7:$E$1006,$B12,Transactions!$I$7:$I$1006,H$6)) | I12: =IF($B12="","",SUMIFS(Transactions!$F$7:$F$1006,Transactions!$D$7:$D$1006,"Income",Transactions!$E$7:$E$1006,$B12,Transactions!$I$7:$I$1006,I$6)) | J12: =IF($B12="","",SUMIFS(Transactions!$F$7:$F$1006,Transactions!$D$7:$D$1006,"Income",Transactions!$E$7:$E$1006,$B12,Transactions!$I$7:$I$1006,J$6)) | ... N12: =IF($B12="","",SUMIFS(Transactions!$F$7:$F$1006,Transactions!$D$7:$D$1006,"Income",Transactions!$E$7:$E$1006,$B12,Transactions!$I$7:$I$1006,N$6)) | O12: =IF($B12="","",SUM(C12:N12)) | P12: =IF($B12="","",IFERROR(O12/MAX(1,COUNTIF(C12:N12,">0")),0))
B13: =IF(Settings!D13="","",Settings!D13) | C13: =IF($B13="","",SUMIFS(Transactions!$F$7:$F$1006,Transactions!$D$7:$D$1006,"Income",Transactions!$E$7:$E$1006,$B13,Transactions!$I$7:$I$1006,C$6)) | D13: =IF($B13="","",SUMIFS(Transactions!$F$7:$F$1006,Transactions!$D$7:$D$1006,"Income",Transactions!$E$7:$E$1006,$B13,Transactions!$I$7:$I$1006,D$6)) | E13: =IF($B13="","",SUMIFS(Transactions!$F$7:$F$1006,Transactions!$D$7:$D$1006,"Income",Transactions!$E$7:$E$1006,$B13,Transactions!$I$7:$I$1006,E$6)) | F13: =IF($B13="","",SUMIFS(Transactions!$F$7:$F$1006,Transactions!$D$7:$D$1006,"Income",Transactions!$E$7:$E$1006,$B13,Transactions!$I$7:$I$1006,F$6)) | G13: =IF($B13="","",SUMIFS(Transactions!$F$7:$F$1006,Transactions!$D$7:$D$1006,"Income",Transactions!$E$7:$E$1006,$B13,Transactions!$I$7:$I$1006,G$6)) | H13: =IF($B13="","",SUMIFS(Transactions!$F$7:$F$1006,Transactions!$D$7:$D$1006,"Income",Transactions!$E$7:$E$1006,$B13,Transactions!$I$7:$I$1006,H$6)) | I13: =IF($B13="","",SUMIFS(Transactions!$F$7:$F$1006,Transactions!$D$7:$D$1006,"Income",Transactions!$E$7:$E$1006,$B13,Transactions!$I$7:$I$1006,I$6)) | J13: =IF($B13="","",SUMIFS(Transactions!$F$7:$F$1006,Transactions!$D$7:$D$1006,"Income",Transactions!$E$7:$E$1006,$B13,Transactions!$I$7:$I$1006,J$6)) | ... N13: =IF($B13="","",SUMIFS(Transactions!$F$7:$F$1006,Transactions!$D$7:$D$1006,"Income",Transactions!$E$7:$E$1006,$B13,Transactions!$I$7:$I$1006,N$6)) | O13: =IF($B13="","",SUM(C13:N13)) | P13: =IF($B13="","",IFERROR(O13/MAX(1,COUNTIF(C13:N13,">0")),0))
B14: =IF(Settings!D14="","",Settings!D14) | C14: =IF($B14="","",SUMIFS(Transactions!$F$7:$F$1006,Transactions!$D$7:$D$1006,"Income",Transactions!$E$7:$E$1006,$B14,Transactions!$I$7:$I$1006,C$6)) | D14: =IF($B14="","",SUMIFS(Transactions!$F$7:$F$1006,Transactions!$D$7:$D$1006,"Income",Transactions!$E$7:$E$1006,$B14,Transactions!$I$7:$I$1006,D$6)) | E14: =IF($B14="","",SUMIFS(Transactions!$F$7:$F$1006,Transactions!$D$7:$D$1006,"Income",Transactions!$E$7:$E$1006,$B14,Transactions!$I$7:$I$1006,E$6)) | F14: =IF($B14="","",SUMIFS(Transactions!$F$7:$F$1006,Transactions!$D$7:$D$1006,"Income",Transactions!$E$7:$E$1006,$B14,Transactions!$I$7:$I$1006,F$6)) | G14: =IF($B14="","",SUMIFS(Transactions!$F$7:$F$1006,Transactions!$D$7:$D$1006,"Income",Transactions!$E$7:$E$1006,$B14,Transactions!$I$7:$I$1006,G$6)) | H14: =IF($B14="","",SUMIFS(Transactions!$F$7:$F$1006,Transactions!$D$7:$D$1006,"Income",Transactions!$E$7:$E$1006,$B14,Transactions!$I$7:$I$1006,H$6)) | I14: =IF($B14="","",SUMIFS(Transactions!$F$7:$F$1006,Transactions!$D$7:$D$1006,"Income",Transactions!$E$7:$E$1006,$B14,Transactions!$I$7:$I$1006,I$6)) | J14: =IF($B14="","",SUMIFS(Transactions!$F$7:$F$1006,Transactions!$D$7:$D$1006,"Income",Transactions!$E$7:$E$1006,$B14,Transactions!$I$7:$I$1006,J$6)) | ... N14: =IF($B14="","",SUMIFS(Transactions!$F$7:$F$1006,Transactions!$D$7:$D$1006,"Income",Transactions!$E$7:$E$1006,$B14,Transactions!$I$7:$I$1006,N$6)) | O14: =IF($B14="","",SUM(C14:N14)) | P14: =IF($B14="","",IFERROR(O14/MAX(1,COUNTIF(C14:N14,">0")),0))
B15: =IF(Settings!D15="","",Settings!D15) | C15: =IF($B15="","",SUMIFS(Transactions!$F$7:$F$1006,Transactions!$D$7:$D$1006,"Income",Transactions!$E$7:$E$1006,$B15,Transactions!$I$7:$I$1006,C$6)) | D15: =IF($B15="","",SUMIFS(Transactions!$F$7:$F$1006,Transactions!$D$7:$D$1006,"Income",Transactions!$E$7:$E$1006,$B15,Transactions!$I$7:$I$1006,D$6)) | E15: =IF($B15="","",SUMIFS(Transactions!$F$7:$F$1006,Transactions!$D$7:$D$1006,"Income",Transactions!$E$7:$E$1006,$B15,Transactions!$I$7:$I$1006,E$6)) | F15: =IF($B15="","",SUMIFS(Transactions!$F$7:$F$1006,Transactions!$D$7:$D$1006,"Income",Transactions!$E$7:$E$1006,$B15,Transactions!$I$7:$I$1006,F$6)) | G15: =IF($B15="","",SUMIFS(Transactions!$F$7:$F$1006,Transactions!$D$7:$D$1006,"Income",Transactions!$E$7:$E$1006,$B15,Transactions!$I$7:$I$1006,G$6)) | H15: =IF($B15="","",SUMIFS(Transactions!$F$7:$F$1006,Transactions!$D$7:$D$1006,"Income",Transactions!$E$7:$E$1006,$B15,Transactions!$I$7:$I$1006,H$6)) | I15: =IF($B15="","",SUMIFS(Transactions!$F$7:$F$1006,Transactions!$D$7:$D$1006,"Income",Transactions!$E$7:$E$1006,$B15,Transactions!$I$7:$I$1006,I$6)) | J15: =IF($B15="","",SUMIFS(Transactions!$F$7:$F$1006,Transactions!$D$7:$D$1006,"Income",Transactions!$E$7:$E$1006,$B15,Transactions!$I$7:$I$1006,J$6)) | ... N15: =IF($B15="","",SUMIFS(Transactions!$F$7:$F$1006,Transactions!$D$7:$D$1006,"Income",Transactions!$E$7:$E$1006,$B15,Transactions!$I$7:$I$1006,N$6)) | O15: =IF($B15="","",SUM(C15:N15)) | P15: =IF($B15="","",IFERROR(O15/MAX(1,COUNTIF(C15:N15,">0")),0))
B16: =IF(Settings!D16="","",Settings!D16) | C16: =IF($B16="","",SUMIFS(Transactions!$F$7:$F$1006,Transactions!$D$7:$D$1006,"Income",Transactions!$E$7:$E$1006,$B16,Transactions!$I$7:$I$1006,C$6)) | D16: =IF($B16="","",SUMIFS(Transactions!$F$7:$F$1006,Transactions!$D$7:$D$1006,"Income",Transactions!$E$7:$E$1006,$B16,Transactions!$I$7:$I$1006,D$6)) | E16: =IF($B16="","",SUMIFS(Transactions!$F$7:$F$1006,Transactions!$D$7:$D$1006,"Income",Transactions!$E$7:$E$1006,$B16,Transactions!$I$7:$I$1006,E$6)) | F16: =IF($B16="","",SUMIFS(Transactions!$F$7:$F$1006,Transactions!$D$7:$D$1006,"Income",Transactions!$E$7:$E$1006,$B16,Transactions!$I$7:$I$1006,F$6)) | G16: =IF($B16="","",SUMIFS(Transactions!$F$7:$F$1006,Transactions!$D$7:$D$1006,"Income",Transactions!$E$7:$E$1006,$B16,Transactions!$I$7:$I$1006,G$6)) | H16: =IF($B16="","",SUMIFS(Transactions!$F$7:$F$1006,Transactions!$D$7:$D$1006,"Income",Transactions!$E$7:$E$1006,$B16,Transactions!$I$7:$I$1006,H$6)) | I16: =IF($B16="","",SUMIFS(Transactions!$F$7:$F$1006,Transactions!$D$7:$D$1006,"Income",Transactions!$E$7:$E$1006,$B16,Transactions!$I$7:$I$1006,I$6)) | J16: =IF($B16="","",SUMIFS(Transactions!$F$7:$F$1006,Transactions!$D$7:$D$1006,"Income",Transactions!$E$7:$E$1006,$B16,Transactions!$I$7:$I$1006,J$6)) | ... N16: =IF($B16="","",SUMIFS(Transactions!$F$7:$F$1006,Transactions!$D$7:$D$1006,"Income",Transactions!$E$7:$E$1006,$B16,Transactions!$I$7:$I$1006,N$6)) | O16: =IF($B16="","",SUM(C16:N16)) | P16: =IF($B16="","",IFERROR(O16/MAX(1,COUNTIF(C16:N16,">0")),0))
B17: =IF(Settings!D17="","",Settings!D17) | C17: =IF($B17="","",SUMIFS(Transactions!$F$7:$F$1006,Transactions!$D$7:$D$1006,"Income",Transactions!$E$7:$E$1006,$B17,Transactions!$I$7:$I$1006,C$6)) | D17: =IF($B17="","",SUMIFS(Transactions!$F$7:$F$1006,Transactions!$D$7:$D$1006,"Income",Transactions!$E$7:$E$1006,$B17,Transactions!$I$7:$I$1006,D$6)) | E17: =IF($B17="","",SUMIFS(Transactions!$F$7:$F$1006,Transactions!$D$7:$D$1006,"Income",Transactions!$E$7:$E$1006,$B17,Transactions!$I$7:$I$1006,E$6)) | F17: =IF($B17="","",SUMIFS(Transactions!$F$7:$F$1006,Transactions!$D$7:$D$1006,"Income",Transactions!$E$7:$E$1006,$B17,Transactions!$I$7:$I$1006,F$6)) | G17: =IF($B17="","",SUMIFS(Transactions!$F$7:$F$1006,Transactions!$D$7:$D$1006,"Income",Transactions!$E$7:$E$1006,$B17,Transactions!$I$7:$I$1006,G$6)) | H17: =IF($B17="","",SUMIFS(Transactions!$F$7:$F$1006,Transactions!$D$7:$D$1006,"Income",Transactions!$E$7:$E$1006,$B17,Transactions!$I$7:$I$1006,H$6)) | I17: =IF($B17="","",SUMIFS(Transactions!$F$7:$F$1006,Transactions!$D$7:$D$1006,"Income",Transactions!$E$7:$E$1006,$B17,Transactions!$I$7:$I$1006,I$6)) | J17: =IF($B17="","",SUMIFS(Transactions!$F$7:$F$1006,Transactions!$D$7:$D$1006,"Income",Transactions!$E$7:$E$1006,$B17,Transactions!$I$7:$I$1006,J$6)) | ... N17: =IF($B17="","",SUMIFS(Transactions!$F$7:$F$1006,Transactions!$D$7:$D$1006,"Income",Transactions!$E$7:$E$1006,$B17,Transactions!$I$7:$I$1006,N$6)) | O17: =IF($B17="","",SUM(C17:N17)) | P17: =IF($B17="","",IFERROR(O17/MAX(1,COUNTIF(C17:N17,">0")),0))
B18: Total income | C18: =SUM(C8:C17) | D18: =SUM(D8:D17) | E18: =SUM(E8:E17) | F18: =SUM(F8:F17) | G18: =SUM(G8:G17) | H18: =SUM(H8:H17) | I18: =SUM(I8:I17) | J18: =SUM(J8:J17) | ... P18: =SUM(P8:P17)
B20: EXPENSES
B21: =IF(Settings!B8="","",Settings!B8) | C21: =IF($B21="","",SUMIFS(Transactions!$F$7:$F$1006,Transactions!$D$7:$D$1006,"Expense",Transactions!$E$7:$E$1006,$B21,Transactions!$I$7:$I$1006,C$6)) | D21: =IF($B21="","",SUMIFS(Transactions!$F$7:$F$1006,Transactions!$D$7:$D$1006,"Expense",Transactions!$E$7:$E$1006,$B21,Transactions!$I$7:$I$1006,D$6)) | E21: =IF($B21="","",SUMIFS(Transactions!$F$7:$F$1006,Transactions!$D$7:$D$1006,"Expense",Transactions!$E$7:$E$1006,$B21,Transactions!$I$7:$I$1006,E$6)) | F21: =IF($B21="","",SUMIFS(Transactions!$F$7:$F$1006,Transactions!$D$7:$D$1006,"Expense",Transactions!$E$7:$E$1006,$B21,Transactions!$I$7:$I$1006,F$6)) | G21: =IF($B21="","",SUMIFS(Transactions!$F$7:$F$1006,Transactions!$D$7:$D$1006,"Expense",Transactions!$E$7:$E$1006,$B21,Transactions!$I$7:$I$1006,G$6)) | H21: =IF($B21="","",SUMIFS(Transactions!$F$7:$F$1006,Transactions!$D$7:$D$1006,"Expense",Transactions!$E$7:$E$1006,$B21,Transactions!$I$7:$I$1006,H$6)) | I21: =IF($B21="","",SUMIFS(Transactions!$F$7:$F$1006,Transactions!$D$7:$D$1006,"Expense",Transactions!$E$7:$E$1006,$B21,Transactions!$I$7:$I$1006,I$6)) | J21: =IF($B21="","",SUMIFS(Transactions!$F$7:$F$1006,Transactions!$D$7:$D$1006,"Expense",Transactions!$E$7:$E$1006,$B21,Transactions!$I$7:$I$1006,J$6)) | ... N21: =IF($B21="","",SUMIFS(Transactions!$F$7:$F$1006,Transactions!$D$7:$D$1006,"Expense",Transactions!$E$7:$E$1006,$B21,Transactions!$I$7:$I$1006,N$6)) | O21: =IF($B21="","",SUM(C21:N21)) | P21: =IF($B21="","",IFERROR(O21/MAX(1,COUNTIF(C21:N21,">0")),0))
B22: =IF(Settings!B9="","",Settings!B9) | C22: =IF($B22="","",SUMIFS(Transactions!$F$7:$F$1006,Transactions!$D$7:$D$1006,"Expense",Transactions!$E$7:$E$1006,$B22,Transactions!$I$7:$I$1006,C$6)) | D22: =IF($B22="","",SUMIFS(Transactions!$F$7:$F$1006,Transactions!$D$7:$D$1006,"Expense",Transactions!$E$7:$E$1006,$B22,Transactions!$I$7:$I$1006,D$6)) | E22: =IF($B22="","",SUMIFS(Transactions!$F$7:$F$1006,Transactions!$D$7:$D$1006,"Expense",Transactions!$E$7:$E$1006,$B22,Transactions!$I$7:$I$1006,E$6)) | F22: =IF($B22="","",SUMIFS(Transactions!$F$7:$F$1006,Transactions!$D$7:$D$1006,"Expense",Transactions!$E$7:$E$1006,$B22,Transactions!$I$7:$I$1006,F$6)) | G22: =IF($B22="","",SUMIFS(Transactions!$F$7:$F$1006,Transactions!$D$7:$D$1006,"Expense",Transactions!$E$7:$E$1006,$B22,Transactions!$I$7:$I$1006,G$6)) | H22: =IF($B22="","",SUMIFS(Transactions!$F$7:$F$1006,Transactions!$D$7:$D$1006,"Expense",Transactions!$E$7:$E$1006,$B22,Transactions!$I$7:$I$1006,H$6)) | I22: =IF($B22="","",SUMIFS(Transactions!$F$7:$F$1006,Transactions!$D$7:$D$1006,"Expense",Transactions!$E$7:$E$1006,$B22,Transactions!$I$7:$I$1006,I$6)) | J22: =IF($B22="","",SUMIFS(Transactions!$F$7:$F$1006,Transactions!$D$7:$D$1006,"Expense",Transactions!$E$7:$E$1006,$B22,Transactions!$I$7:$I$1006,J$6)) | ... N22: =IF($B22="","",SUMIFS(Transactions!$F$7:$F$1006,Transactions!$D$7:$D$1006,"Expense",Transactions!$E$7:$E$1006,$B22,Transactions!$I$7:$I$1006,N$6)) | O22: =IF($B22="","",SUM(C22:N22)) | P22: =IF($B22="","",IFERROR(O22/MAX(1,COUNTIF(C22:N22,">0")),0))
B23: =IF(Settings!B10="","",Settings!B10) | C23: =IF($B23="","",SUMIFS(Transactions!$F$7:$F$1006,Transactions!$D$7:$D$1006,"Expense",Transactions!$E$7:$E$1006,$B23,Transactions!$I$7:$I$1006,C$6)) | D23: =IF($B23="","",SUMIFS(Transactions!$F$7:$F$1006,Transactions!$D$7:$D$1006,"Expense",Transactions!$E$7:$E$1006,$B23,Transactions!$I$7:$I$1006,D$6)) | E23: =IF($B23="","",SUMIFS(Transactions!$F$7:$F$1006,Transactions!$D$7:$D$1006,"Expense",Transactions!$E$7:$E$1006,$B23,Transactions!$I$7:$I$1006,E$6)) | F23: =IF($B23="","",SUMIFS(Transactions!$F$7:$F$1006,Transactions!$D$7:$D$1006,"Expense",Transactions!$E$7:$E$1006,$B23,Transactions!$I$7:$I$1006,F$6)) | G23: =IF($B23="","",SUMIFS(Transactions!$F$7:$F$1006,Transactions!$D$7:$D$1006,"Expense",Transactions!$E$7:$E$1006,$B23,Transactions!$I$7:$I$1006,G$6)) | H23: =IF($B23="","",SUMIFS(Transactions!$F$7:$F$1006,Transactions!$D$7:$D$1006,"Expense",Transactions!$E$7:$E$1006,$B23,Transactions!$I$7:$I$1006,H$6)) | I23: =IF($B23="","",SUMIFS(Transactions!$F$7:$F$1006,Transactions!$D$7:$D$1006,"Expense",Transactions!$E$7:$E$1006,$B23,Transactions!$I$7:$I$1006,I$6)) | J23: =IF($B23="","",SUMIFS(Transactions!$F$7:$F$1006,Transactions!$D$7:$D$1006,"Expense",Transactions!$E$7:$E$1006,$B23,Transactions!$I$7:$I$1006,J$6)) | ... N23: =IF($B23="","",SUMIFS(Transactions!$F$7:$F$1006,Transactions!$D$7:$D$1006,"Expense",Transactions!$E$7:$E$1006,$B23,Transactions!$I$7:$I$1006,N$6)) | O23: =IF($B23="","",SUM(C23:N23)) | P23: =IF($B23="","",IFERROR(O23/MAX(1,COUNTIF(C23:N23,">0")),0))
B24: =IF(Settings!B11="","",Settings!B11) | C24: =IF($B24="","",SUMIFS(Transactions!$F$7:$F$1006,Transactions!$D$7:$D$1006,"Expense",Transactions!$E$7:$E$1006,$B24,Transactions!$I$7:$I$1006,C$6)) | D24: =IF($B24="","",SUMIFS(Transactions!$F$7:$F$1006,Transactions!$D$7:$D$1006,"Expense",Transactions!$E$7:$E$1006,$B24,Transactions!$I$7:$I$1006,D$6)) | E24: =IF($B24="","",SUMIFS(Transactions!$F$7:$F$1006,Transactions!$D$7:$D$1006,"Expense",Transactions!$E$7:$E$1006,$B24,Transactions!$I$7:$I$1006,E$6)) | F24: =IF($B24="","",SUMIFS(Transactions!$F$7:$F$1006,Transactions!$D$7:$D$1006,"Expense",Transactions!$E$7:$E$1006,$B24,Transactions!$I$7:$I$1006,F$6)) | G24: =IF($B24="","",SUMIFS(Transactions!$F$7:$F$1006,Transactions!$D$7:$D$1006,"Expense",Transactions!$E$7:$E$1006,$B24,Transactions!$I$7:$I$1006,G$6)) | H24: =IF($B24="","",SUMIFS(Transactions!$F$7:$F$1006,Transactions!$D$7:$D$1006,"Expense",Transactions!$E$7:$E$1006,$B24,Transactions!$I$7:$I$1006,H$6)) | I24: =IF($B24="","",SUMIFS(Transactions!$F$7:$F$1006,Transactions!$D$7:$D$1006,"Expense",Transactions!$E$7:$E$1006,$B24,Transactions!$I$7:$I$1006,I$6)) | J24: =IF($B24="","",SUMIFS(Transactions!$F$7:$F$1006,Transactions!$D$7:$D$1006,"Expense",Transactions!$E$7:$E$1006,$B24,Transactions!$I$7:$I$1006,J$6)) | ... N24: =IF($B24="","",SUMIFS(Transactions!$F$7:$F$1006,Transactions!$D$7:$D$1006,"Expense",Transactions!$E$7:$E$1006,$B24,Transactions!$I$7:$I$1006,N$6)) | O24: =IF($B24="","",SUM(C24:N24)) | P24: =IF($B24="","",IFERROR(O24/MAX(1,COUNTIF(C24:N24,">0")),0))
B25: =IF(Settings!B12="","",Settings!B12) | C25: =IF($B25="","",SUMIFS(Transactions!$F$7:$F$1006,Transactions!$D$7:$D$1006,"Expense",Transactions!$E$7:$E$1006,$B25,Transactions!$I$7:$I$1006,C$6)) | D25: =IF($B25="","",SUMIFS(Transactions!$F$7:$F$1006,Transactions!$D$7:$D$1006,"Expense",Transactions!$E$7:$E$1006,$B25,Transactions!$I$7:$I$1006,D$6)) | E25: =IF($B25="","",SUMIFS(Transactions!$F$7:$F$1006,Transactions!$D$7:$D$1006,"Expense",Transactions!$E$7:$E$1006,$B25,Transactions!$I$7:$I$1006,E$6)) | F25: =IF($B25="","",SUMIFS(Transactions!$F$7:$F$1006,Transactions!$D$7:$D$1006,"Expense",Transactions!$E$7:$E$1006,$B25,Transactions!$I$7:$I$1006,F$6)) | G25: =IF($B25="","",SUMIFS(Transactions!$F$7:$F$1006,Transactions!$D$7:$D$1006,"Expense",Transactions!$E$7:$E$1006,$B25,Transactions!$I$7:$I$1006,G$6)) | H25: =IF($B25="","",SUMIFS(Transactions!$F$7:$F$1006,Transactions!$D$7:$D$1006,"Expense",Transactions!$E$7:$E$1006,$B25,Transactions!$I$7:$I$1006,H$6)) | I25: =IF($B25="","",SUMIFS(Transactions!$F$7:$F$1006,Transactions!$D$7:$D$1006,"Expense",Transactions!$E$7:$E$1006,$B25,Transactions!$I$7:$I$1006,I$6)) | J25: =IF($B25="","",SUMIFS(Transactions!$F$7:$F$1006,Transactions!$D$7:$D$1006,"Expense",Transactions!$E$7:$E$1006,$B25,Transactions!$I$7:$I$1006,J$6)) | ... N25: =IF($B25="","",SUMIFS(Transactions!$F$7:$F$1006,Transactions!$D$7:$D$1006,"Expense",Transactions!$E$7:$E$1006,$B25,Transactions!$I$7:$I$1006,N$6)) | O25: =IF($B25="","",SUM(C25:N25)) | P25: =IF($B25="","",IFERROR(O25/MAX(1,COUNTIF(C25:N25,">0")),0))
B26: =IF(Settings!B13="","",Settings!B13) | C26: =IF($B26="","",SUMIFS(Transactions!$F$7:$F$1006,Transactions!$D$7:$D$1006,"Expense",Transactions!$E$7:$E$1006,$B26,Transactions!$I$7:$I$1006,C$6)) | D26: =IF($B26="","",SUMIFS(Transactions!$F$7:$F$1006,Transactions!$D$7:$D$1006,"Expense",Transactions!$E$7:$E$1006,$B26,Transactions!$I$7:$I$1006,D$6)) | E26: =IF($B26="","",SUMIFS(Transactions!$F$7:$F$1006,Transactions!$D$7:$D$1006,"Expense",Transactions!$E$7:$E$1006,$B26,Transactions!$I$7:$I$1006,E$6)) | F26: =IF($B26="","",SUMIFS(Transactions!$F$7:$F$1006,Transactions!$D$7:$D$1006,"Expense",Transactions!$E$7:$E$1006,$B26,Transactions!$I$7:$I$1006,F$6)) | G26: =IF($B26="","",SUMIFS(Transactions!$F$7:$F$1006,Transactions!$D$7:$D$1006,"Expense",Transactions!$E$7:$E$1006,$B26,Transactions!$I$7:$I$1006,G$6)) | H26: =IF($B26="","",SUMIFS(Transactions!$F$7:$F$1006,Transactions!$D$7:$D$1006,"Expense",Transactions!$E$7:$E$1006,$B26,Transactions!$I$7:$I$1006,H$6)) | I26: =IF($B26="","",SUMIFS(Transactions!$F$7:$F$1006,Transactions!$D$7:$D$1006,"Expense",Transactions!$E$7:$E$1006,$B26,Transactions!$I$7:$I$1006,I$6)) | J26: =IF($B26="","",SUMIFS(Transactions!$F$7:$F$1006,Transactions!$D$7:$D$1006,"Expense",Transactions!$E$7:$E$1006,$B26,Transactions!$I$7:$I$1006,J$6)) | ... N26: =IF($B26="","",SUMIFS(Transactions!$F$7:$F$1006,Transactions!$D$7:$D$1006,"Expense",Transactions!$E$7:$E$1006,$B26,Transactions!$I$7:$I$1006,N$6)) | O26: =IF($B26="","",SUM(C26:N26)) | P26: =IF($B26="","",IFERROR(O26/MAX(1,COUNTIF(C26:N26,">0")),0))
B27: =IF(Settings!B14="","",Settings!B14) | C27: =IF($B27="","",SUMIFS(Transactions!$F$7:$F$1006,Transactions!$D$7:$D$1006,"Expense",Transactions!$E$7:$E$1006,$B27,Transactions!$I$7:$I$1006,C$6)) | D27: =IF($B27="","",SUMIFS(Transactions!$F$7:$F$1006,Transactions!$D$7:$D$1006,"Expense",Transactions!$E$7:$E$1006,$B27,Transactions!$I$7:$I$1006,D$6)) | E27: =IF($B27="","",SUMIFS(Transactions!$F$7:$F$1006,Transactions!$D$7:$D$1006,"Expense",Transactions!$E$7:$E$1006,$B27,Transactions!$I$7:$I$1006,E$6)) | F27: =IF($B27="","",SUMIFS(Transactions!$F$7:$F$1006,Transactions!$D$7:$D$1006,"Expense",Transactions!$E$7:$E$1006,$B27,Transactions!$I$7:$I$1006,F$6)) | G27: =IF($B27="","",SUMIFS(Transactions!$F$7:$F$1006,Transactions!$D$7:$D$1006,"Expense",Transactions!$E$7:$E$1006,$B27,Transactions!$I$7:$I$1006,G$6)) | H27: =IF($B27="","",SUMIFS(Transactions!$F$7:$F$1006,Transactions!$D$7:$D$1006,"Expense",Transactions!$E$7:$E$1006,$B27,Transactions!$I$7:$I$1006,H$6)) | I27: =IF($B27="","",SUMIFS(Transactions!$F$7:$F$1006,Transactions!$D$7:$D$1006,"Expense",Transactions!$E$7:$E$1006,$B27,Transactions!$I$7:$I$1006,I$6)) | J27: =IF($B27="","",SUMIFS(Transactions!$F$7:$F$1006,Transactions!$D$7:$D$1006,"Expense",Transactions!$E$7:$E$1006,$B27,Transactions!$I$7:$I$1006,J$6)) | ... N27: =IF($B27="","",SUMIFS(Transactions!$F$7:$F$1006,Transactions!$D$7:$D$1006,"Expense",Transactions!$E$7:$E$1006,$B27,Transactions!$I$7:$I$1006,N$6)) | O27: =IF($B27="","",SUM(C27:N27)) | P27: =IF($B27="","",IFERROR(O27/MAX(1,COUNTIF(C27:N27,">0")),0))
B28: =IF(Settings!B15="","",Settings!B15) | C28: =IF($B28="","",SUMIFS(Transactions!$F$7:$F$1006,Transactions!$D$7:$D$1006,"Expense",Transactions!$E$7:$E$1006,$B28,Transactions!$I$7:$I$1006,C$6)) | D28: =IF($B28="","",SUMIFS(Transactions!$F$7:$F$1006,Transactions!$D$7:$D$1006,"Expense",Transactions!$E$7:$E$1006,$B28,Transactions!$I$7:$I$1006,D$6)) | E28: =IF($B28="","",SUMIFS(Transactions!$F$7:$F$1006,Transactions!$D$7:$D$1006,"Expense",Transactions!$E$7:$E$1006,$B28,Transactions!$I$7:$I$1006,E$6)) | F28: =IF($B28="","",SUMIFS(Transactions!$F$7:$F$1006,Transactions!$D$7:$D$1006,"Expense",Transactions!$E$7:$E$1006,$B28,Transactions!$I$7:$I$1006,F$6)) | G28: =IF($B28="","",SUMIFS(Transactions!$F$7:$F$1006,Transactions!$D$7:$D$1006,"Expense",Transactions!$E$7:$E$1006,$B28,Transactions!$I$7:$I$1006,G$6)) | H28: =IF($B28="","",SUMIFS(Transactions!$F$7:$F$1006,Transactions!$D$7:$D$1006,"Expense",Transactions!$E$7:$E$1006,$B28,Transactions!$I$7:$I$1006,H$6)) | I28: =IF($B28="","",SUMIFS(Transactions!$F$7:$F$1006,Transactions!$D$7:$D$1006,"Expense",Transactions!$E$7:$E$1006,$B28,Transactions!$I$7:$I$1006,I$6)) | J28: =IF($B28="","",SUMIFS(Transactions!$F$7:$F$1006,Transactions!$D$7:$D$1006,"Expense",Transactions!$E$7:$E$1006,$B28,Transactions!$I$7:$I$1006,J$6)) | ... N28: =IF($B28="","",SUMIFS(Transactions!$F$7:$F$1006,Transactions!$D$7:$D$1006,"Expense",Transactions!$E$7:$E$1006,$B28,Transactions!$I$7:$I$1006,N$6)) | O28: =IF($B28="","",SUM(C28:N28)) | P28: =IF($B28="","",IFERROR(O28/MAX(1,COUNTIF(C28:N28,">0")),0))
B29: =IF(Settings!B16="","",Settings!B16) | C29: =IF($B29="","",SUMIFS(Transactions!$F$7:$F$1006,Transactions!$D$7:$D$1006,"Expense",Transactions!$E$7:$E$1006,$B29,Transactions!$I$7:$I$1006,C$6)) | D29: =IF($B29="","",SUMIFS(Transactions!$F$7:$F$1006,Transactions!$D$7:$D$1006,"Expense",Transactions!$E$7:$E$1006,$B29,Transactions!$I$7:$I$1006,D$6)) | E29: =IF($B29="","",SUMIFS(Transactions!$F$7:$F$1006,Transactions!$D$7:$D$1006,"Expense",Transactions!$E$7:$E$1006,$B29,Transactions!$I$7:$I$1006,E$6)) | F29: =IF($B29="","",SUMIFS(Transactions!$F$7:$F$1006,Transactions!$D$7:$D$1006,"Expense",Transactions!$E$7:$E$1006,$B29,Transactions!$I$7:$I$1006,F$6)) | G29: =IF($B29="","",SUMIFS(Transactions!$F$7:$F$1006,Transactions!$D$7:$D$1006,"Expense",Transactions!$E$7:$E$1006,$B29,Transactions!$I$7:$I$1006,G$6)) | H29: =IF($B29="","",SUMIFS(Transactions!$F$7:$F$1006,Transactions!$D$7:$D$1006,"Expense",Transactions!$E$7:$E$1006,$B29,Transactions!$I$7:$I$1006,H$6)) | I29: =IF($B29="","",SUMIFS(Transactions!$F$7:$F$1006,Transactions!$D$7:$D$1006,"Expense",Transactions!$E$7:$E$1006,$B29,Transactions!$I$7:$I$1006,I$6)) | J29: =IF($B29="","",SUMIFS(Transactions!$F$7:$F$1006,Transactions!$D$7:$D$1006,"Expense",Transactions!$E$7:$E$1006,$B29,Transactions!$I$7:$I$1006,J$6)) | ... N29: =IF($B29="","",SUMIFS(Transactions!$F$7:$F$1006,Transactions!$D$7:$D$1006,"Expense",Transactions!$E$7:$E$1006,$B29,Transactions!$I$7:$I$1006,N$6)) | O29: =IF($B29="","",SUM(C29:N29)) | P29: =IF($B29="","",IFERROR(O29/MAX(1,COUNTIF(C29:N29,">0")),0))
B30: =IF(Settings!B17="","",Settings!B17) | C30: =IF($B30="","",SUMIFS(Transactions!$F$7:$F$1006,Transactions!$D$7:$D$1006,"Expense",Transactions!$E$7:$E$1006,$B30,Transactions!$I$7:$I$1006,C$6)) | D30: =IF($B30="","",SUMIFS(Transactions!$F$7:$F$1006,Transactions!$D$7:$D$1006,"Expense",Transactions!$E$7:$E$1006,$B30,Transactions!$I$7:$I$1006,D$6)) | E30: =IF($B30="","",SUMIFS(Transactions!$F$7:$F$1006,Transactions!$D$7:$D$1006,"Expense",Transactions!$E$7:$E$1006,$B30,Transactions!$I$7:$I$1006,E$6)) | F30: =IF($B30="","",SUMIFS(Transactions!$F$7:$F$1006,Transactions!$D$7:$D$1006,"Expense",Transactions!$E$7:$E$1006,$B30,Transactions!$I$7:$I$1006,F$6)) | G30: =IF($B30="","",SUMIFS(Transactions!$F$7:$F$1006,Transactions!$D$7:$D$1006,"Expense",Transactions!$E$7:$E$1006,$B30,Transactions!$I$7:$I$1006,G$6)) | H30: =IF($B30="","",SUMIFS(Transactions!$F$7:$F$1006,Transactions!$D$7:$D$1006,"Expense",Transactions!$E$7:$E$1006,$B30,Transactions!$I$7:$I$1006,H$6)) | I30: =IF($B30="","",SUMIFS(Transactions!$F$7:$F$1006,Transactions!$D$7:$D$1006,"Expense",Transactions!$E$7:$E$1006,$B30,Transactions!$I$7:$I$1006,I$6)) | J30: =IF($B30="","",SUMIFS(Transactions!$F$7:$F$1006,Transactions!$D$7:$D$1006,"Expense",Transactions!$E$7:$E$1006,$B30,Transactions!$I$7:$I$1006,J$6)) | ... N30: =IF($B30="","",SUMIFS(Transactions!$F$7:$F$1006,Transactions!$D$7:$D$1006,"Expense",Transactions!$E$7:$E$1006,$B30,Transactions!$I$7:$I$1006,N$6)) | O30: =IF($B30="","",SUM(C30:N30)) | P30: =IF($B30="","",IFERROR(O30/MAX(1,COUNTIF(C30:N30,">0")),0))
B31: =IF(Settings!B18="","",Settings!B18) | C31: =IF($B31="","",SUMIFS(Transactions!$F$7:$F$1006,Transactions!$D$7:$D$1006,"Expense",Transactions!$E$7:$E$1006,$B31,Transactions!$I$7:$I$1006,C$6)) | D31: =IF($B31="","",SUMIFS(Transactions!$F$7:$F$1006,Transactions!$D$7:$D$1006,"Expense",Transactions!$E$7:$E$1006,$B31,Transactions!$I$7:$I$1006,D$6)) | E31: =IF($B31="","",SUMIFS(Transactions!$F$7:$F$1006,Transactions!$D$7:$D$1006,"Expense",Transactions!$E$7:$E$1006,$B31,Transactions!$I$7:$I$1006,E$6)) | F31: =IF($B31="","",SUMIFS(Transactions!$F$7:$F$1006,Transactions!$D$7:$D$1006,"Expense",Transactions!$E$7:$E$1006,$B31,Transactions!$I$7:$I$1006,F$6)) | G31: =IF($B31="","",SUMIFS(Transactions!$F$7:$F$1006,Transactions!$D$7:$D$1006,"Expense",Transactions!$E$7:$E$1006,$B31,Transactions!$I$7:$I$1006,G$6)) | H31: =IF($B31="","",SUMIFS(Transactions!$F$7:$F$1006,Transactions!$D$7:$D$1006,"Expense",Transactions!$E$7:$E$1006,$B31,Transactions!$I$7:$I$1006,H$6)) | I31: =IF($B31="","",SUMIFS(Transactions!$F$7:$F$1006,Transactions!$D$7:$D$1006,"Expense",Transactions!$E$7:$E$1006,$B31,Transactions!$I$7:$I$1006,I$6)) | J31: =IF($B31="","",SUMIFS(Transactions!$F$7:$F$1006,Transactions!$D$7:$D$1006,"Expense",Transactions!$E$7:$E$1006,$B31,Transactions!$I$7:$I$1006,J$6)) | ... N31: =IF($B31="","",SUMIFS(Transactions!$F$7:$F$1006,Transactions!$D$7:$D$1006,"Expense",Transactions!$E$7:$E$1006,$B31,Transactions!$I$7:$I$1006,N$6)) | O31: =IF($B31="","",SUM(C31:N31)) | P31: =IF($B31="","",IFERROR(O31/MAX(1,COUNTIF(C31:N31,">0")),0))
B32: =IF(Settings!B19="","",Settings!B19) | C32: =IF($B32="","",SUMIFS(Transactions!$F$7:$F$1006,Transactions!$D$7:$D$1006,"Expense",Transactions!$E$7:$E$1006,$B32,Transactions!$I$7:$I$1006,C$6)) | D32: =IF($B32="","",SUMIFS(Transactions!$F$7:$F$1006,Transactions!$D$7:$D$1006,"Expense",Transactions!$E$7:$E$1006,$B32,Transactions!$I$7:$I$1006,D$6)) | E32: =IF($B32="","",SUMIFS(Transactions!$F$7:$F$1006,Transactions!$D$7:$D$1006,"Expense",Transactions!$E$7:$E$1006,$B32,Transactions!$I$7:$I$1006,E$6)) | F32: =IF($B32="","",SUMIFS(Transactions!$F$7:$F$1006,Transactions!$D$7:$D$1006,"Expense",Transactions!$E$7:$E$1006,$B32,Transactions!$I$7:$I$1006,F$6)) | G32: =IF($B32="","",SUMIFS(Transactions!$F$7:$F$1006,Transactions!$D$7:$D$1006,"Expense",Transactions!$E$7:$E$1006,$B32,Transactions!$I$7:$I$1006,G$6)) | H32: =IF($B32="","",SUMIFS(Transactions!$F$7:$F$1006,Transactions!$D$7:$D$1006,"Expense",Transactions!$E$7:$E$1006,$B32,Transactions!$I$7:$I$1006,H$6)) | I32: =IF($B32="","",SUMIFS(Transactions!$F$7:$F$1006,Transactions!$D$7:$D$1006,"Expense",Transactions!$E$7:$E$1006,$B32,Transactions!$I$7:$I$1006,I$6)) | J32: =IF($B32="","",SUMIFS(Transactions!$F$7:$F$1006,Transactions!$D$7:$D$1006,"Expense",Transactions!$E$7:$E$1006,$B32,Transactions!$I$7:$I$1006,J$6)) | ... N32: =IF($B32="","",SUMIFS(Transactions!$F$7:$F$1006,Transactions!$D$7:$D$1006,"Expense",Transactions!$E$7:$E$1006,$B32,Transactions!$I$7:$I$1006,N$6)) | O32: =IF($B32="","",SUM(C32:N32)) | P32: =IF($B32="","",IFERROR(O32/MAX(1,COUNTIF(C32:N32,">0")),0))
... B50: =IF(Settings!B37="","",Settings!B37) | C50: =IF($B50="","",SUMIFS(Transactions!$F$7:$F$1006,Transactions!$D$7:$D$1006,"Expense",Transactions!$E$7:$E$1006,$B50,Transactions!$I$7:$I$1006,C$6)) | D50: =IF($B50="","",SUMIFS(Transactions!$F$7:$F$1006,Transactions!$D$7:$D$1006,"Expense",Transactions!$E$7:$E$1006,$B50,Transactions!$I$7:$I$1006,D$6)) | E50: =IF($B50="","",SUMIFS(Transactions!$F$7:$F$1006,Transactions!$D$7:$D$1006,"Expense",Transactions!$E$7:$E$1006,$B50,Transactions!$I$7:$I$1006,E$6)) | F50: =IF($B50="","",SUMIFS(Transactions!$F$7:$F$1006,Transactions!$D$7:$D$1006,"Expense",Transactions!$E$7:$E$1006,$B50,Transactions!$I$7:$I$1006,F$6)) | G50: =IF($B50="","",SUMIFS(Transactions!$F$7:$F$1006,Transactions!$D$7:$D$1006,"Expense",Transactions!$E$7:$E$1006,$B50,Transactions!$I$7:$I$1006,G$6)) | H50: =IF($B50="","",SUMIFS(Transactions!$F$7:$F$1006,Transactions!$D$7:$D$1006,"Expense",Transactions!$E$7:$E$1006,$B50,Transactions!$I$7:$I$1006,H$6)) | I50: =IF($B50="","",SUMIFS(Transactions!$F$7:$F$1006,Transactions!$D$7:$D$1006,"Expense",Transactions!$E$7:$E$1006,$B50,Transactions!$I$7:$I$1006,I$6)) | J50: =IF($B50="","",SUMIFS(Transactions!$F$7:$F$1006,Transactions!$D$7:$D$1006,"Expense",Transactions!$E$7:$E$1006,$B50,Transactions!$I$7:$I$1006,J$6)) | ... N50: =IF($B50="","",SUMIFS(Transactions!$F$7:$F$1006,Transactions!$D$7:$D$1006,"Expense",Transactions!$E$7:$E$1006,$B50,Transactions!$I$7:$I$1006,N$6)) | O50: =IF($B50="","",SUM(C50:N50)) | P50: =IF($B50="","",IFERROR(O50/MAX(1,COUNTIF(C50:N50,">0")),0))
B51: Total expenses | C51: =SUM(C21:C50) | D51: =SUM(D21:D50) | E51: =SUM(E21:E50) | F51: =SUM(F21:F50) | G51: =SUM(G21:G50) | H51: =SUM(H21:H50) | I51: =SUM(I21:I50) | J51: =SUM(J21:J50) | ... P51: =SUM(P21:P50)
B52: Left over | C52: =C18-C51 | D52: =D18-D51 | E52: =E18-E51 | F52: =F18-F51 | G52: =G18-G51 | H52: =H18-H51 | I52: =I18-I51 | J52: =J18-J51 | ... O52: =O18-O51
B53: Savings rate | C53: =IF(C18=0,0,C52/C18) | D53: =IF(D18=0,0,D52/D18) | E53: =IF(E18=0,0,E52/E18) | F53: =IF(F18=0,0,F52/F18) | G53: =IF(G18=0,0,G52/G18) | H53: =IF(H18=0,0,H52/H18) | I53: =IF(I18=0,0,I52/I18) | J53: =IF(J18=0,0,J52/J18) | ... O53: =IF(O18=0,0,O52/O18)

Sheet Savings Goals
B2: Savings Goals & Sinking Funds
B3: One row per goal. Update 'Saved so far' whenever you move money. Progress and monthly need are automatic.
B5: Today's date | C5: =TODAY()
B7: Goal | C7: Target amount | D7: Saved so far | E7: Remaining | F7: Progress | G7: Target date | H7: Months left | I7: Save per month | J7: Status
B8: Emergency fund | C8: 6000 | D8: 2150 | E8: =IF(B8="","",MAX(0,C8-D8)) | F8: =IF(OR(B8="",C8=0),"",MIN(1,D8/C8)) | G8: 46568 | H8: =IF(OR(B8="",G8=""),"",MAX(0,(YEAR(G8)-YEAR($C$5))*12+MONTH(G8)-MONTH($C$5))) | I8: =IF(OR(B8="",G8=""),"",IF(E8=0,0,IF(H8=0,E8,E8/H8))) | J8: =IF(B8="","",IF(E8=0,"Done ✓",IF(G8="","No date",IF(H8=0,"Due now","On track"))))
B9: Vacation | C9: 1800 | D9: 400 | E9: =IF(B9="","",MAX(0,C9-D9)) | F9: =IF(OR(B9="",C9=0),"",MIN(1,D9/C9)) | G9: 46447 | H9: =IF(OR(B9="",G9=""),"",MAX(0,(YEAR(G9)-YEAR($C$5))*12+MONTH(G9)-MONTH($C$5))) | I9: =IF(OR(B9="",G9=""),"",IF(E9=0,0,IF(H9=0,E9,E9/H9))) | J9: =IF(B9="","",IF(E9=0,"Done ✓",IF(G9="","No date",IF(H9=0,"Due now","On track"))))
B10: New laptop | C10: 1400 | D10: 1400 | E10: =IF(B10="","",MAX(0,C10-D10)) | F10: =IF(OR(B10="",C10=0),"",MIN(1,D10/C10)) | G10: 46357 | H10: =IF(OR(B10="",G10=""),"",MAX(0,(YEAR(G10)-YEAR($C$5))*12+MONTH(G10)-MONTH($C$5))) | I10: =IF(OR(B10="",G10=""),"",IF(E10=0,0,IF(H10=0,E10,E10/H10))) | J10: =IF(B10="","",IF(E10=0,"Done ✓",IF(G10="","No date",IF(H10=0,"Due now","On track"))))
B11: Car repairs fund | C11: 1000 | D11: 250 | E11: =IF(B11="","",MAX(0,C11-D11)) | F11: =IF(OR(B11="",C11=0),"",MIN(1,D11/C11)) | G11: 46418 | H11: =IF(OR(B11="",G11=""),"",MAX(0,(YEAR(G11)-YEAR($C$5))*12+MONTH(G11)-MONTH($C$5))) | I11: =IF(OR(B11="",G11=""),"",IF(E11=0,0,IF(H11=0,E11,E11/H11))) | J11: =IF(B11="","",IF(E11=0,"Done ✓",IF(G11="","No date",IF(H11=0,"Due now","On track"))))
B12: Holiday gifts | C12: 600 | D12: 120 | E12: =IF(B12="","",MAX(0,C12-D12)) | F12: =IF(OR(B12="",C12=0),"",MIN(1,D12/C12)) | G12: 46366 | H12: =IF(OR(B12="",G12=""),"",MAX(0,(YEAR(G12)-YEAR($C$5))*12+MONTH(G12)-MONTH($C$5))) | I12: =IF(OR(B12="",G12=""),"",IF(E12=0,0,IF(H12=0,E12,E12/H12))) | J12: =IF(B12="","",IF(E12=0,"Done ✓",IF(G12="","No date",IF(H12=0,"Due now","On track"))))
E13: =IF(B13="","",MAX(0,C13-D13)) | F13: =IF(OR(B13="",C13=0),"",MIN(1,D13/C13)) | H13: =IF(OR(B13="",G13=""),"",MAX(0,(YEAR(G13)-YEAR($C$5))*12+MONTH(G13)-MONTH($C$5))) | I13: =IF(OR(B13="",G13=""),"",IF(E13=0,0,IF(H13=0,E13,E13/H13))) | J13: =IF(B13="","",IF(E13=0,"Done ✓",IF(G13="","No date",IF(H13=0,"Due now","On track"))))
E14: =IF(B14="","",MAX(0,C14-D14)) | F14: =IF(OR(B14="",C14=0),"",MIN(1,D14/C14)) | H14: =IF(OR(B14="",G14=""),"",MAX(0,(YEAR(G14)-YEAR($C$5))*12+MONTH(G14)-MONTH($C$5))) | I14: =IF(OR(B14="",G14=""),"",IF(E14=0,0,IF(H14=0,E14,E14/H14))) | J14: =IF(B14="","",IF(E14=0,"Done ✓",IF(G14="","No date",IF(H14=0,"Due now","On track"))))
E15: =IF(B15="","",MAX(0,C15-D15)) | F15: =IF(OR(B15="",C15=0),"",MIN(1,D15/C15)) | H15: =IF(OR(B15="",G15=""),"",MAX(0,(YEAR(G15)-YEAR($C$5))*12+MONTH(G15)-MONTH($C$5))) | I15: =IF(OR(B15="",G15=""),"",IF(E15=0,0,IF(H15=0,E15,E15/H15))) | J15: =IF(B15="","",IF(E15=0,"Done ✓",IF(G15="","No date",IF(H15=0,"Due now","On track"))))
E16: =IF(B16="","",MAX(0,C16-D16)) | F16: =IF(OR(B16="",C16=0),"",MIN(1,D16/C16)) | H16: =IF(OR(B16="",G16=""),"",MAX(0,(YEAR(G16)-YEAR($C$5))*12+MONTH(G16)-MONTH($C$5))) | I16: =IF(OR(B16="",G16=""),"",IF(E16=0,0,IF(H16=0,E16,E16/H16))) | J16: =IF(B16="","",IF(E16=0,"Done ✓",IF(G16="","No date",IF(H16=0,"Due now","On track"))))
E17: =IF(B17="","",MAX(0,C17-D17)) | F17: =IF(OR(B17="",C17=0),"",MIN(1,D17/C17)) | H17: =IF(OR(B17="",G17=""),"",MAX(0,(YEAR(G17)-YEAR($C$5))*12+MONTH(G17)-MONTH($C$5))) | I17: =IF(OR(B17="",G17=""),"",IF(E17=0,0,IF(H17=0,E17,E17/H17))) | J17: =IF(B17="","",IF(E17=0,"Done ✓",IF(G17="","No date",IF(H17=0,"Due now","On track"))))
E18: =IF(B18="","",MAX(0,C18-D18)) | F18: =IF(OR(B18="",C18=0),"",MIN(1,D18/C18)) | H18: =IF(OR(B18="",G18=""),"",MAX(0,(YEAR(G18)-YEAR($C$5))*12+MONTH(G18)-MONTH($C$5))) | I18: =IF(OR(B18="",G18=""),"",IF(E18=0,0,IF(H18=0,E18,E18/H18))) | J18: =IF(B18="","",IF(E18=0,"Done ✓",IF(G18="","No date",IF(H18=0,"Due now","On track"))))
E19: =IF(B19="","",MAX(0,C19-D19)) | F19: =IF(OR(B19="",C19=0),"",MIN(1,D19/C19)) | H19: =IF(OR(B19="",G19=""),"",MAX(0,(YEAR(G19)-YEAR($C$5))*12+MONTH(G19)-MONTH($C$5))) | I19: =IF(OR(B19="",G19=""),"",IF(E19=0,0,IF(H19=0,E19,E19/H19))) | J19: =IF(B19="","",IF(E19=0,"Done ✓",IF(G19="","No date",IF(H19=0,"Due now","On track"))))
E20: =IF(B20="","",MAX(0,C20-D20)) | F20: =IF(OR(B20="",C20=0),"",MIN(1,D20/C20)) | H20: =IF(OR(B20="",G20=""),"",MAX(0,(YEAR(G20)-YEAR($C$5))*12+MONTH(G20)-MONTH($C$5))) | I20: =IF(OR(B20="",G20=""),"",IF(E20=0,0,IF(H20=0,E20,E20/H20))) | J20: =IF(B20="","",IF(E20=0,"Done ✓",IF(G20="","No date",IF(H20=0,"Due now","On track"))))
E21: =IF(B21="","",MAX(0,C21-D21)) | F21: =IF(OR(B21="",C21=0),"",MIN(1,D21/C21)) | H21: =IF(OR(B21="",G21=""),"",MAX(0,(YEAR(G21)-YEAR($C$5))*12+MONTH(G21)-MONTH($C$5))) | I21: =IF(OR(B21="",G21=""),"",IF(E21=0,0,IF(H21=0,E21,E21/H21))) | J21: =IF(B21="","",IF(E21=0,"Done ✓",IF(G21="","No date",IF(H21=0,"Due now","On track"))))
E22: =IF(B22="","",MAX(0,C22-D22)) | F22: =IF(OR(B22="",C22=0),"",MIN(1,D22/C22)) | H22: =IF(OR(B22="",G22=""),"",MAX(0,(YEAR(G22)-YEAR($C$5))*12+MONTH(G22)-MONTH($C$5))) | I22: =IF(OR(B22="",G22=""),"",IF(E22=0,0,IF(H22=0,E22,E22/H22))) | J22: =IF(B22="","",IF(E22=0,"Done ✓",IF(G22="","No date",IF(H22=0,"Due now","On track"))))
E23: =IF(B23="","",MAX(0,C23-D23)) | F23: =IF(OR(B23="",C23=0),"",MIN(1,D23/C23)) | H23: =IF(OR(B23="",G23=""),"",MAX(0,(YEAR(G23)-YEAR($C$5))*12+MONTH(G23)-MONTH($C$5))) | I23: =IF(OR(B23="",G23=""),"",IF(E23=0,0,IF(H23=0,E23,E23/H23))) | J23: =IF(B23="","",IF(E23=0,"Done ✓",IF(G23="","No date",IF(H23=0,"Due now","On track"))))
E24: =IF(B24="","",MAX(0,C24-D24)) | F24: =IF(OR(B24="",C24=0),"",MIN(1,D24/C24)) | H24: =IF(OR(B24="",G24=""),"",MAX(0,(YEAR(G24)-YEAR($C$5))*12+MONTH(G24)-MONTH($C$5))) | I24: =IF(OR(B24="",G24=""),"",IF(E24=0,0,IF(H24=0,E24,E24/H24))) | J24: =IF(B24="","",IF(E24=0,"Done ✓",IF(G24="","No date",IF(H24=0,"Due now","On track"))))
... E27: =IF(B27="","",MAX(0,C27-D27)) | F27: =IF(OR(B27="",C27=0),"",MIN(1,D27/C27)) | H27: =IF(OR(B27="",G27=""),"",MAX(0,(YEAR(G27)-YEAR($C$5))*12+MONTH(G27)-MONTH($C$5))) | I27: =IF(OR(B27="",G27=""),"",IF(E27=0,0,IF(H27=0,E27,E27/H27))) | J27: =IF(B27="","",IF(E27=0,"Done ✓",IF(G27="","No date",IF(H27=0,"Due now","On track"))))
B29: Totals | C29: =SUM(C8:C27) | D29: =SUM(D8:D27) | E29: =SUM(E8:E27) | I29: =SUM(I8:I27)
B31: Example goals shown – replace with yours. 'Save per month' = remaining ÷ months left until the target date.

Sheet Debt Payoff
B2: Debt Payoff Planner
B3: List each debt. Choose Snowball (smallest balance first) or Avalanche (highest rate first). Estimates assume fixed payments and no new charges.
B5: Method | C5: Avalanche | E5: Extra you can pay per month | G5: 150
B7: Debt | C7: Balance | D7: APR % | E7: Minimum payment | F7: Payoff order | G7: Months at minimum | H7: Interest at minimum (est.) | I7: Monthly interest now | J7: Note
B8: Credit card A | C8: 3200 | D8: 0.2499 | E8: 95 | F8: =IF(B8="","",IF($C$5="Snowball",SUMPRODUCT(($B$8:$B$22<>"")*($C$8:$C$22<C8))+SUMPRODUCT(($B$8:$B$22<>"")*($C$8:$C$22=C8)*(ROW($B$8:$B$22)<8))+1,SUMPRODUCT(($B$8:$B$22<>"")*($D$8:$D$22>D8))+SUMPRODUCT(($B$8:$B$22<>"")*($D$8:$D$22=D8)*(ROW($B$8:$B$22)<8))+1)) | G8: =IF(B8="","",IF(E8<=C8*D8/12,"Never – raise payment",IFERROR(ROUNDUP(NPER(D8/12,-E8,C8),0),ROUNDUP(C8/MAX(E8,1),0)))) | H8: =IF(OR(B8="",NOT(ISNUMBER(G8))),"",G8*E8-C8) | I8: =IF(B8="","",C8*D8/12)
B9: Car loan | C9: 8900 | D9: 0.069 | E9: 265 | F9: =IF(B9="","",IF($C$5="Snowball",SUMPRODUCT(($B$8:$B$22<>"")*($C$8:$C$22<C9))+SUMPRODUCT(($B$8:$B$22<>"")*($C$8:$C$22=C9)*(ROW($B$8:$B$22)<9))+1,SUMPRODUCT(($B$8:$B$22<>"")*($D$8:$D$22>D9))+SUMPRODUCT(($B$8:$B$22<>"")*($D$8:$D$22=D9)*(ROW($B$8:$B$22)<9))+1)) | G9: =IF(B9="","",IF(E9<=C9*D9/12,"Never – raise payment",IFERROR(ROUNDUP(NPER(D9/12,-E9,C9),0),ROUNDUP(C9/MAX(E9,1),0)))) | H9: =IF(OR(B9="",NOT(ISNUMBER(G9))),"",G9*E9-C9) | I9: =IF(B9="","",C9*D9/12)
B10: Student loan | C10: 12400 | D10: 0.055 | E10: 140 | F10: =IF(B10="","",IF($C$5="Snowball",SUMPRODUCT(($B$8:$B$22<>"")*($C$8:$C$22<C10))+SUMPRODUCT(($B$8:$B$22<>"")*($C$8:$C$22=C10)*(ROW($B$8:$B$22)<10))+1,SUMPRODUCT(($B$8:$B$22<>"")*($D$8:$D$22>D10))+SUMPRODUCT(($B$8:$B$22<>"")*($D$8:$D$22=D10)*(ROW($B$8:$B$22)<10))+1)) | G10: =IF(B10="","",IF(E10<=C10*D10/12,"Never – raise payment",IFERROR(ROUNDUP(NPER(D10/12,-E10,C10),0),ROUNDUP(C10/MAX(E10,1),0)))) | H10: =IF(OR(B10="",NOT(ISNUMBER(G10))),"",G10*E10-C10) | I10: =IF(B10="","",C10*D10/12)
B11: Store card | C11: 640 | D11: 0.2899 | E11: 30 | F11: =IF(B11="","",IF($C$5="Snowball",SUMPRODUCT(($B$8:$B$22<>"")*($C$8:$C$22<C11))+SUMPRODUCT(($B$8:$B$22<>"")*($C$8:$C$22=C11)*(ROW($B$8:$B$22)<11))+1,SUMPRODUCT(($B$8:$B$22<>"")*($D$8:$D$22>D11))+SUMPRODUCT(($B$8:$B$22<>"")*($D$8:$D$22=D11)*(ROW($B$8:$B$22)<11))+1)) | G11: =IF(B11="","",IF(E11<=C11*D11/12,"Never – raise payment",IFERROR(ROUNDUP(NPER(D11/12,-E11,C11),0),ROUNDUP(C11/MAX(E11,1),0)))) | H11: =IF(OR(B11="",NOT(ISNUMBER(G11))),"",G11*E11-C11) | I11: =IF(B11="","",C11*D11/12)
F12: =IF(B12="","",IF($C$5="Snowball",SUMPRODUCT(($B$8:$B$22<>"")*($C$8:$C$22<C12))+SUMPRODUCT(($B$8:$B$22<>"")*($C$8:$C$22=C12)*(ROW($B$8:$B$22)<12))+1,SUMPRODUCT(($B$8:$B$22<>"")*($D$8:$D$22>D12))+SUMPRODUCT(($B$8:$B$22<>"")*($D$8:$D$22=D12)*(ROW($B$8:$B$22)<12))+1)) | G12: =IF(B12="","",IF(E12<=C12*D12/12,"Never – raise payment",IFERROR(ROUNDUP(NPER(D12/12,-E12,C12),0),ROUNDUP(C12/MAX(E12,1),0)))) | H12: =IF(OR(B12="",NOT(ISNUMBER(G12))),"",G12*E12-C12) | I12: =IF(B12="","",C12*D12/12)
F13: =IF(B13="","",IF($C$5="Snowball",SUMPRODUCT(($B$8:$B$22<>"")*($C$8:$C$22<C13))+SUMPRODUCT(($B$8:$B$22<>"")*($C$8:$C$22=C13)*(ROW($B$8:$B$22)<13))+1,SUMPRODUCT(($B$8:$B$22<>"")*($D$8:$D$22>D13))+SUMPRODUCT(($B$8:$B$22<>"")*($D$8:$D$22=D13)*(ROW($B$8:$B$22)<13))+1)) | G13: =IF(B13="","",IF(E13<=C13*D13/12,"Never – raise payment",IFERROR(ROUNDUP(NPER(D13/12,-E13,C13),0),ROUNDUP(C13/MAX(E13,1),0)))) | H13: =IF(OR(B13="",NOT(ISNUMBER(G13))),"",G13*E13-C13) | I13: =IF(B13="","",C13*D13/12)
F14: =IF(B14="","",IF($C$5="Snowball",SUMPRODUCT(($B$8:$B$22<>"")*($C$8:$C$22<C14))+SUMPRODUCT(($B$8:$B$22<>"")*($C$8:$C$22=C14)*(ROW($B$8:$B$22)<14))+1,SUMPRODUCT(($B$8:$B$22<>"")*($D$8:$D$22>D14))+SUMPRODUCT(($B$8:$B$22<>"")*($D$8:$D$22=D14)*(ROW($B$8:$B$22)<14))+1)) | G14: =IF(B14="","",IF(E14<=C14*D14/12,"Never – raise payment",IFERROR(ROUNDUP(NPER(D14/12,-E14,C14),0),ROUNDUP(C14/MAX(E14,1),0)))) | H14: =IF(OR(B14="",NOT(ISNUMBER(G14))),"",G14*E14-C14) | I14: =IF(B14="","",C14*D14/12)
F15: =IF(B15="","",IF($C$5="Snowball",SUMPRODUCT(($B$8:$B$22<>"")*($C$8:$C$22<C15))+SUMPRODUCT(($B$8:$B$22<>"")*($C$8:$C$22=C15)*(ROW($B$8:$B$22)<15))+1,SUMPRODUCT(($B$8:$B$22<>"")*($D$8:$D$22>D15))+SUMPRODUCT(($B$8:$B$22<>"")*($D$8:$D$22=D15)*(ROW($B$8:$B$22)<15))+1)) | G15: =IF(B15="","",IF(E15<=C15*D15/12,"Never – raise payment",IFERROR(ROUNDUP(NPER(D15/12,-E15,C15),0),ROUNDUP(C15/MAX(E15,1),0)))) | H15: =IF(OR(B15="",NOT(ISNUMBER(G15))),"",G15*E15-C15) | I15: =IF(B15="","",C15*D15/12)
F16: =IF(B16="","",IF($C$5="Snowball",SUMPRODUCT(($B$8:$B$22<>"")*($C$8:$C$22<C16))+SUMPRODUCT(($B$8:$B$22<>"")*($C$8:$C$22=C16)*(ROW($B$8:$B$22)<16))+1,SUMPRODUCT(($B$8:$B$22<>"")*($D$8:$D$22>D16))+SUMPRODUCT(($B$8:$B$22<>"")*($D$8:$D$22=D16)*(ROW($B$8:$B$22)<16))+1)) | G16: =IF(B16="","",IF(E16<=C16*D16/12,"Never – raise payment",IFERROR(ROUNDUP(NPER(D16/12,-E16,C16),0),ROUNDUP(C16/MAX(E16,1),0)))) | H16: =IF(OR(B16="",NOT(ISNUMBER(G16))),"",G16*E16-C16) | I16: =IF(B16="","",C16*D16/12)
F17: =IF(B17="","",IF($C$5="Snowball",SUMPRODUCT(($B$8:$B$22<>"")*($C$8:$C$22<C17))+SUMPRODUCT(($B$8:$B$22<>"")*($C$8:$C$22=C17)*(ROW($B$8:$B$22)<17))+1,SUMPRODUCT(($B$8:$B$22<>"")*($D$8:$D$22>D17))+SUMPRODUCT(($B$8:$B$22<>"")*($D$8:$D$22=D17)*(ROW($B$8:$B$22)<17))+1)) | G17: =IF(B17="","",IF(E17<=C17*D17/12,"Never – raise payment",IFERROR(ROUNDUP(NPER(D17/12,-E17,C17),0),ROUNDUP(C17/MAX(E17,1),0)))) | H17: =IF(OR(B17="",NOT(ISNUMBER(G17))),"",G17*E17-C17) | I17: =IF(B17="","",C17*D17/12)
F18: =IF(B18="","",IF($C$5="Snowball",SUMPRODUCT(($B$8:$B$22<>"")*($C$8:$C$22<C18))+SUMPRODUCT(($B$8:$B$22<>"")*($C$8:$C$22=C18)*(ROW($B$8:$B$22)<18))+1,SUMPRODUCT(($B$8:$B$22<>"")*($D$8:$D$22>D18))+SUMPRODUCT(($B$8:$B$22<>"")*($D$8:$D$22=D18)*(ROW($B$8:$B$22)<18))+1)) | G18: =IF(B18="","",IF(E18<=C18*D18/12,"Never – raise payment",IFERROR(ROUNDUP(NPER(D18/12,-E18,C18),0),ROUNDUP(C18/MAX(E18,1),0)))) | H18: =IF(OR(B18="",NOT(ISNUMBER(G18))),"",G18*E18-C18) | I18: =IF(B18="","",C18*D18/12)
F19: =IF(B19="","",IF($C$5="Snowball",SUMPRODUCT(($B$8:$B$22<>"")*($C$8:$C$22<C19))+SUMPRODUCT(($B$8:$B$22<>"")*($C$8:$C$22=C19)*(ROW($B$8:$B$22)<19))+1,SUMPRODUCT(($B$8:$B$22<>"")*($D$8:$D$22>D19))+SUMPRODUCT(($B$8:$B$22<>"")*($D$8:$D$22=D19)*(ROW($B$8:$B$22)<19))+1)) | G19: =IF(B19="","",IF(E19<=C19*D19/12,"Never – raise payment",IFERROR(ROUNDUP(NPER(D19/12,-E19,C19),0),ROUNDUP(C19/MAX(E19,1),0)))) | H19: =IF(OR(B19="",NOT(ISNUMBER(G19))),"",G19*E19-C19) | I19: =IF(B19="","",C19*D19/12)
F20: =IF(B20="","",IF($C$5="Snowball",SUMPRODUCT(($B$8:$B$22<>"")*($C$8:$C$22<C20))+SUMPRODUCT(($B$8:$B$22<>"")*($C$8:$C$22=C20)*(ROW($B$8:$B$22)<20))+1,SUMPRODUCT(($B$8:$B$22<>"")*($D$8:$D$22>D20))+SUMPRODUCT(($B$8:$B$22<>"")*($D$8:$D$22=D20)*(ROW($B$8:$B$22)<20))+1)) | G20: =IF(B20="","",IF(E20<=C20*D20/12,"Never – raise payment",IFERROR(ROUNDUP(NPER(D20/12,-E20,C20),0),ROUNDUP(C20/MAX(E20,1),0)))) | H20: =IF(OR(B20="",NOT(ISNUMBER(G20))),"",G20*E20-C20) | I20: =IF(B20="","",C20*D20/12)
F21: =IF(B21="","",IF($C$5="Snowball",SUMPRODUCT(($B$8:$B$22<>"")*($C$8:$C$22<C21))+SUMPRODUCT(($B$8:$B$22<>"")*($C$8:$C$22=C21)*(ROW($B$8:$B$22)<21))+1,SUMPRODUCT(($B$8:$B$22<>"")*($D$8:$D$22>D21))+SUMPRODUCT(($B$8:$B$22<>"")*($D$8:$D$22=D21)*(ROW($B$8:$B$22)<21))+1)) | G21: =IF(B21="","",IF(E21<=C21*D21/12,"Never – raise payment",IFERROR(ROUNDUP(NPER(D21/12,-E21,C21),0),ROUNDUP(C21/MAX(E21,1),0)))) | H21: =IF(OR(B21="",NOT(ISNUMBER(G21))),"",G21*E21-C21) | I21: =IF(B21="","",C21*D21/12)
F22: =IF(B22="","",IF($C$5="Snowball",SUMPRODUCT(($B$8:$B$22<>"")*($C$8:$C$22<C22))+SUMPRODUCT(($B$8:$B$22<>"")*($C$8:$C$22=C22)*(ROW($B$8:$B$22)<22))+1,SUMPRODUCT(($B$8:$B$22<>"")*($D$8:$D$22>D22))+SUMPRODUCT(($B$8:$B$22<>"")*($D$8:$D$22=D22)*(ROW($B$8:$B$22)<22))+1)) | G22: =IF(B22="","",IF(E22<=C22*D22/12,"Never – raise payment",IFERROR(ROUNDUP(NPER(D22/12,-E22,C22),0),ROUNDUP(C22/MAX(E22,1),0)))) | H22: =IF(OR(B22="",NOT(ISNUMBER(G22))),"",G22*E22-C22) | I22: =IF(B22="","",C22*D22/12)
B24: Totals | C24: =SUM(C8:C22) | E24: =SUM(E8:E22) | I24: =SUM(I8:I22)
B26: How to use the plan
B27: 1. Pay the minimum on every debt.
B28: 2. Send the 'extra' amount (cell G5) to the debt with Payoff order = 1 (highlighted).
B29: 3. When it's paid off, add its old minimum to the extra and move to order 2. Repeat.
B30: Snowball = quick wins (smallest balance first). Avalanche = least interest overall (highest APR first). Both work — pick the one you'll stick with.
B31: Estimates only. They assume fixed payments, no new charges, and simple monthly compounding. Your lender's statement is the source of truth.

Sheet Net Worth
B2: Net Worth Tracker
B3: Once a month, type your balances. Net worth = what you own − what you owe.
B6: Month | C6: Cash & checking | D6: Savings | E6: Investments / retirement | F6: Home / car value | G6: Other assets | H6: TOTAL ASSETS | I6: Credit cards | J6: Loans | K6: Mortgage | L6: Other debts | M6: TOTAL DEBTS | N6: NET WORTH | O6: Change
B7: =DATE(Settings!$C$5,1,1) | C7: 2400 | D7: 6100 | E7: 15200 | F7: 0 | G7: 0 | H7: =SUM(C7:G7) | I7: 3200 | J7: 8900 | K7: 0 | L7: 0 | M7: =SUM(I7:L7) | N7: =IF(AND(H7=0,M7=0),"",H7-M7)
B8: =DATE(YEAR(B7),MONTH(B7)+1,1) | C8: 2650 | D8: 6500 | E8: 15650 | F8: 0 | G8: 0 | H8: =SUM(C8:G8) | I8: 3050 | J8: 8635 | K8: 0 | L8: 0 | M8: =SUM(I8:L8) | N8: =IF(AND(H8=0,M8=0),"",H8-M8) | O8: =IF(OR(N8="",N7=""),"",N8-N7)
B9: =DATE(YEAR(B8),MONTH(B8)+1,1) | C9: 2100 | D9: 6900 | E9: 15900 | F9: 0 | G9: 0 | H9: =SUM(C9:G9) | I9: 2900 | J9: 8370 | K9: 0 | L9: 0 | M9: =SUM(I9:L9) | N9: =IF(AND(H9=0,M9=0),"",H9-M9) | O9: =IF(OR(N9="",N8=""),"",N9-N8)
B10: =DATE(YEAR(B9),MONTH(B9)+1,1) | H10: =SUM(C10:G10) | M10: =SUM(I10:L10) | N10: =IF(AND(H10=0,M10=0),"",H10-M10) | O10: =IF(OR(N10="",N9=""),"",N10-N9)
B11: =DATE(YEAR(B10),MONTH(B10)+1,1) | H11: =SUM(C11:G11) | M11: =SUM(I11:L11) | N11: =IF(AND(H11=0,M11=0),"",H11-M11) | O11: =IF(OR(N11="",N10=""),"",N11-N10)
B12: =DATE(YEAR(B11),MONTH(B11)+1,1) | H12: =SUM(C12:G12) | M12: =SUM(I12:L12) | N12: =IF(AND(H12=0,M12=0),"",H12-M12) | O12: =IF(OR(N12="",N11=""),"",N12-N11)
B13: =DATE(YEAR(B12),MONTH(B12)+1,1) | H13: =SUM(C13:G13) | M13: =SUM(I13:L13) | N13: =IF(AND(H13=0,M13=0),"",H13-M13) | O13: =IF(OR(N13="",N12=""),"",N13-N12)
B14: =DATE(YEAR(B13),MONTH(B13)+1,1) | H14: =SUM(C14:G14) | M14: =SUM(I14:L14) | N14: =IF(AND(H14=0,M14=0),"",H14-M14) | O14: =IF(OR(N14="",N13=""),"",N14-N13)
B15: =DATE(YEAR(B14),MONTH(B14)+1,1) | H15: =SUM(C15:G15) | M15: =SUM(I15:L15) | N15: =IF(AND(H15=0,M15=0),"",H15-M15) | O15: =IF(OR(N15="",N14=""),"",N15-N14)
B16: =DATE(YEAR(B15),MONTH(B15)+1,1) | H16: =SUM(C16:G16) | M16: =SUM(I16:L16) | N16: =IF(AND(H16=0,M16=0),"",H16-M16) | O16: =IF(OR(N16="",N15=""),"",N16-N15)
B17: =DATE(YEAR(B16),MONTH(B16)+1,1) | H17: =SUM(C17:G17) | M17: =SUM(I17:L17) | N17: =IF(AND(H17=0,M17=0),"",H17-M17) | O17: =IF(OR(N17="",N16=""),"",N17-N16)
B18: =DATE(YEAR(B17),MONTH(B17)+1,1) | H18: =SUM(C18:G18) | M18: =SUM(I18:L18) | N18: =IF(AND(H18=0,M18=0),"",H18-M18) | O18: =IF(OR(N18="",N17=""),"",N18-N17)
B19: =DATE(YEAR(B18),MONTH(B18)+1,1) | H19: =SUM(C19:G19) | M19: =SUM(I19:L19) | N19: =IF(AND(H19=0,M19=0),"",H19-M19) | O19: =IF(OR(N19="",N18=""),"",N19-N18)
B20: =DATE(YEAR(B19),MONTH(B19)+1,1) | H20: =SUM(C20:G20) | M20: =SUM(I20:L20) | N20: =IF(AND(H20=0,M20=0),"",H20-M20) | O20: =IF(OR(N20="",N19=""),"",N20-N19)
B21: =DATE(YEAR(B20),MONTH(B20)+1,1) | H21: =SUM(C21:G21) | M21: =SUM(I21:L21) | N21: =IF(AND(H21=0,M21=0),"",H21-M21) | O21: =IF(OR(N21="",N20=""),"",N21-N20)
... B30: =DATE(YEAR(B29),MONTH(B29)+1,1) | H30: =SUM(C30:G30) | M30: =SUM(I30:L30) | N30: =IF(AND(H30=0,M30=0),"",H30-M30) | O30: =IF(OR(N30="",N29=""),"",N30-N29)
B31: First 3 months are examples – overwrite them.
